[
  {
    "id": 17928992239562644,
    "created_at": 1624382216,
    "text": "Die \"verjudete Schulmedizin\" nannten die Nationalsozialisten es... dass Bakterien oder Viren vor keiner \"Rasse\" halt machen, passte wohl nicht so ganz in ihr Weltbild... Misstrauen gegenüber der medizinischen Wissenschaft würde gern geschürt und stattdessen die Homöopathie bevorzugt und verbreitet.  Bis heute hat sich der negativ besetzte Begriff der \"Schulmedizin\" als Gegenpart zur Homöopathie gehalten. Bis heute schwurbeln diverse Heilpraktiker vor sich hin, verbreiten rechte Esoterikgruppierungen krude \"Wahrheiten\"- derzeit aktuell auch über Coronaviren. Es ist erschreckend...",
    "owner": {
      "id": "XGpCtyp0_Ltalv9nQM0Erg==",
      "username": "FNeOWl5wEXOAqIlfbkZ4-w=="
    },
    "likes_count": 0,
    "answers": []
  },
  {
    "id": 17911057555868543,
    "created_at": 1623944030,
    "text": "@sEvCk0S25YC1oiV3Ta_5yQ==",
    "owner": {
      "id": "gdgTC1Ykc9LBQUK3BRHXcA==",
      "username": "bpjLmIy9JJWDP-EzapGYHw=="
    },
    "likes_count": 0,
    "answers": []
  },
  {
    "id": 17864107592502032,
    "created_at": 1623758792,
    "text": "Es ist so wichtig Dinge zu hinterfragen. Und genau dass hast du in dieser rauen Zeit gemacht. Du hast dir Gedanken gemacht. Du wolltest die Welt verändern. Und das bleibt unvergesslich! 🙌❤️",
    "owner": {
      "id": "TDyJzXAewGUfmkXqRqH3Cg==",
      "username": "iC_963RHjPAZCaYyLXUhbA=="
    },
    "likes_count": 1,
    "answers": []
  },
  {
    "id": 18112701598244280,
    "created_at": 1623738419,
    "text": "Liebe Sophie, als ich vor einem Monat in München war und an der Uni vorbeigefahren bin musste ich an Dich denken. <3",
    "owner": {
      "id": "Zfva3zyGjcMHoBMndJ67JA==",
      "username": "LQJoLxJn6LLQ2X0a5LR_oA=="
    },
    "likes_count": 20,
    "answers": [
      {
        "id": 17917896097738482,
        "created_at": 1623753005,
        "text": "@yewQ-brj1WOqEZOh84QDhA== Das ist aber aufmerksam von dir. Liebe Grüße an dich!",
        "owner": {
          "id": "9rICyTfoSV8xPafAZ0Xo0w==",
          "username": "hib4mKmHA-vgwtwb0Q_04A=="
        },
        "likes_count": 18
      }
    ]
  },
  {
    "id": 17888976485199716,
    "created_at": 1623711388,
    "text": "Ich denke schon, dass es Sinn macht dran zu bleiben - umso mehr wir über diese grauenhaften Theorien wissen, umso besser können wir die Worte wählen die nötig sind, um auch andere dazu zu bewegen das zu erkennen. Und wo wenn nicht an der Uni lassen sich da vielleicht offene Ohren finden!",
    "owner": {
      "id": "Vxx_Z8JvfNIzUB5wRSKmNA==",
      "username": "FXYycXuNTV8rJvguOwXcxA=="
    },
    "likes_count": 8,
    "answers": [
      {
        "id": 17931217054571414,
        "created_at": 1623757320,
        "text": "@FXYycXuNTV8rJvguOwXcxA== Liebe Jasmin, danke gebe ich dir vollkommen Recht. Mir kommt es so vor, als sitzen dort so viele junge Menschen, saugen diese schrecklichen Theorien nur so auf und hinterfragen nicht ein Wort. \nDennoch möchte ich hoffnungsvoll sein und besonders diese Menschen mit unseren Worten erreichen! \nEs fällt mir nur unglaublich schwer da zu sitzen und zu zuhören. Meine Körper weigert sich...",
        "owner": {
          "id": "9rICyTfoSV8xPafAZ0Xo0w==",
          "username": "hib4mKmHA-vgwtwb0Q_04A=="
        },
        "likes_count": 12
      }
    ]
  },
  {
    "id": 17910805621874174,
    "created_at": 1623707324,
    "text": "@eYJiX1aBdC-xDumS1OLVLA==",
    "owner": {
      "id": "bpxgJvHMLA0zuVb748pwGg==",
      "username": "8HIK3Nk2lJgboTmIsVX8pg=="
    },
    "likes_count": 1,
    "answers": []
  },
  {
    "id": 17860895978540119,
    "created_at": 1623699708,
    "text": "Liebe Sophie, ich kann dich verstehen, dass du an deinem Studium zweifelst. Und ich mag auch sagen, dass es dennoch wichtig ist, Menschen wie dich dort zu haben. Vielleicht schaffst du, schafft ihr es anderen eine andere Sicht zu geben, auf den Krieg, auf die Nationalsozialisten. Ich wünsche es euch. 🤗",
    "owner": {
      "id": "R32LkI6djFgBI1W2w6Utiw==",
      "username": "uASpkrNUNe5YeLkUQuU0jw=="
    },
    "likes_count": 10,
    "answers": [
      {
        "id": 17909978845800171,
        "created_at": 1623757364,
        "text": "@uASpkrNUNe5YeLkUQuU0jw== Ich werde es versuchen!",
        "owner": {
          "id": "9rICyTfoSV8xPafAZ0Xo0w==",
          "username": "hib4mKmHA-vgwtwb0Q_04A=="
        },
        "likes_count": 6
      }
    ]
  },
  {
    "id": 18232191415044334,
    "created_at": 1623699511,
    "text": "I feel you",
    "owner": {
      "id": "K8SajkjK0-nMy1iU3cR_WA==",
      "username": "eRRjlX41tPa-WqolrGQXzw=="
    },
    "likes_count": 1,
    "answers": []
  },
  {
    "id": 18167719549132989,
    "created_at": 1623699499,
    "text": "Wie gut bist du in fortnite?",
    "owner": {
      "id": "cRXhVwiJlNVO0woAo65rLw==",
      "username": "Ha8c2WydrSJPfnY4TZn5_w=="
    },
    "likes_count": 2,
    "answers": []
  },
  {
    "id": 17882814866259705,
    "created_at": 1623698275,
    "text": "Ohne Sophiescholl können wir nicht wissen, den kampf gegen rasismus im diese vergangenheit zeiten❤️",
    "owner": {
      "id": "qxmlkMTj7oszt2jETWQ30A==",
      "username": "ukPmzsVq98cPen5_YKFy-Q=="
    },
    "likes_count": 0,
    "answers": []
  },
  {
    "id": 17874832073342358,
    "created_at": 1623694481,
    "text": "Hey Sophie, hast du schon mal Hitler live gesehen ?",
    "owner": {
      "id": "GdufmRMJ0eNAzNoenXCJMw==",
      "username": "Dz1BxKMixAdPH65vD6oNmg=="
    },
    "likes_count": 1,
    "answers": []
  },
  {
    "id": 17922873838657203,
    "created_at": 1623688938,
    "text": "In der Familie, unter Freunden und Bekannten, lernt man viel mehr, als in der Schule.",
    "owner": {
      "id": "zUnKaadbt47ypeemTDwNew==",
      "username": "P9cLGpzDbqMqkmwYbq4xgQ=="
    },
    "likes_count": 1,
    "answers": []
  },
  {
    "id": 17923235875632675,
    "created_at": 1623685914,
    "text": "Die Frage wurde  #teamsoffer mäßig bestimmt schon beantwortet, habe ich dann wohl verpaßt, denke ich. Darum bitte: Was sind das für SW-Filmchen wie heute in der Story? Von Sophie und/oder ihrer Bekannten und Freunde selbst gedreht? Oder welche anderer Zeitgenossen?",
    "owner": {
      "id": "KciJsGrMCjAj_gtM9EXcjQ==",
      "username": "HDCPspSdnHXKb-VWvBWVWg=="
    },
    "likes_count": 15,
    "answers": [
      {
        "id": 17906396518865279,
        "created_at": 1623702735,
        "text": "@hib4mKmHA-vgwtwb0Q_04A== Von welchen Archiven/Agenturen bezieht ihr denn das zeitgenössische Bildmaterial? Vielen Dank im Voraus für die Antwort!",
        "owner": {
          "id": "ooCVZQv7J5c2QX2-wE5GfA==",
          "username": "xT1FMc2FXcT-HAsOeqcjLw=="
        },
        "likes_count": 0
      },
      {
        "id": 17903814844981390,
        "created_at": 1623693445,
        "text": "#teamsoffer Hallo @bemerkenswerth, die Aufnahmen stammen aus einem Archiv. Sie sind aus der selben Zeit, aber nicht von Sophie Scholl gefilmt worden. Beste Grüße!",
        "owner": {
          "id": "9rICyTfoSV8xPafAZ0Xo0w==",
          "username": "hib4mKmHA-vgwtwb0Q_04A=="
        },
        "likes_count": 41
      },
      {
        "id": 17888020580154727,
        "created_at": 1623703926,
        "text": "#teamsoffer @evke_covfefe Das meiste unseres verwendeten Materials aus der damaligen Zeit stammt aus dem AKH Archiv. Liebe Grüße!",
        "owner": {
          "id": "9rICyTfoSV8xPafAZ0Xo0w==",
          "username": "hib4mKmHA-vgwtwb0Q_04A=="
        },
        "likes_count": 10
      }
    ]
  },
  {
    "id": 18076817809281628,
    "created_at": 1623685467,
    "text": "Ich frage mich oft: Wie hätte ich mich verhalten in dieser Zeit? Weggeduckt? Revoltiert?",
    "owner": {
      "id": "kWR8NhTdDYiekwF6N2aJ0w==",
      "username": "eqWumdoXfAdZVxafGf2vyg=="
    },
    "likes_count": 0,
    "answers": []
  },
  {
    "id": 17875657427440681,
    "created_at": 1623683769,
    "text": "Was machst du heute die wundern frau @ichbinsophiescholl",
    "owner": {
      "id": "oyD-ioh_3AbnnD2mVxOqrQ==",
      "username": "He4mYX7fohRkWGWoisZhug=="
    },
    "likes_count": 0,
    "answers": []
  },
  {
    "id": 17976477085389626,
    "created_at": 1623683078,
    "text": "🤗🤗🤗",
    "owner": {
      "id": "hungulOo_zowokq8qI9wPA==",
      "username": "qP5RtR2EeH-2opE8McOGDg=="
    },
    "likes_count": 2,
    "answers": []
  },
  {
    "id": 17923438237632903,
    "created_at": 1623683050,
    "text": "Hallo Sophie, sein deswegen nicht traurig. Was euch die Lehrer in eurer Zeit \"beibringen\" wollen, kann man als frei denkender Mensch für sich selbst abwägen, ob man es sich annimmt oder auch nicht. Immer alles im Leben für sich selbst hinterfragen. Aber deswegen nicht das Studium schmeißen, ein Berufsabschluss ist im Leben extrem wichtig.... 👍",
    "owner": {
      "id": "uHI6FOzdrKjWkn5oBhjQiw==",
      "username": "O8HUKFJKtNPgxm6U3j75BQ=="
    },
    "likes_count": 0,
    "answers": []
  },
  {
    "id": 18092191054256913,
    "created_at": 1623681208,
    "text": "Such pretty eyes 😍",
    "owner": {
      "id": "IdzMISEiR08ZvqEYJL_AAA==",
      "username": "f15z1XG2hQVsIGaV4OTS8g=="
    },
    "likes_count": 2,
    "answers": []
  },
  {
    "id": 18047535160295081,
    "created_at": 1623678635,
    "text": "🔥❤️",
    "owner": {
      "id": "V6FDAaQ-Fuf3hFYiSned6Q==",
      "username": "E9fxFCqe73UMJOXwr8S0CA=="
    },
    "likes_count": 1,
    "answers": []
  },
  {
    "id": 18212236723074013,
    "created_at": 1623678217,
    "text": "Hallo",
    "owner": {
      "id": "zpZMWllYxr6tjAQkZxGXKg==",
      "username": "Iu90Tw_9Bmkzyy05UDgNGg=="
    },
    "likes_count": 1,
    "answers": []
  },
  {
    "id": 17887820612272734,
    "created_at": 1623675878,
    "text": "Schwierige Situation. Folge deinem Herzen - am Ende musst du nur dir Rede und Antwort stehen. ❤️",
    "owner": {
      "id": "N5X2thS-5DmmsNJqosw0ww==",
      "username": "LG2EE1WhqRoBRdzXrebIxA=="
    },
    "likes_count": 3,
    "answers": []
  },
  {
    "id": 17871278246430686,
    "created_at": 1623675428,
    "text": "Bleib stark, mach dein Ding mit den anderen.💪 vllt könnten die Vorlesungen ja insofern wertvoll sein, dass man auch darüber in den Flugblättern aufklärt? Ansonsten, Schein wahren. ❤️",
    "owner": {
      "id": "FGesO6GODe4c7OJd3j-isg==",
      "username": "FRryP4X2VIKFaUGQpPelUA=="
    },
    "likes_count": 2,
    "answers": []
  },
  {
    "id": 17860504694542858,
    "created_at": 1623675046,
    "text": "❤️",
    "owner": {
      "id": "0aWcFa3--r_KXj1tpLFAzQ==",
      "username": "Ab5SnwvpfCr7GnqM2KgxnA=="
    },
    "likes_count": 1,
    "answers": []
  },
  {
    "id": 17915579647749450,
    "created_at": 1623674099,
    "text": "Liebe Sophie, egal was du tust, bitte nicht am 18. Februar mit Koffer voller Flugblättern in die Uni laufen... ihr werdet an diesem Tag auffliegen und dann HINGERICHTET! Bitte Vorsicht also...",
    "owner": {
      "id": "BS0N9xh6TPv53ZklNAmh9w==",
      "username": "Y2Vb8KfCWripB0Y2_19iJg=="
    },
    "likes_count": 2,
    "answers": [
      {
        "id": 17897391530092204,
        "created_at": 1623685381,
        "text": "@PhcL3suZ7R1Wri6_Ndqrug== sie sollen ruhig Flugblätter verteilen das stimmt aber eben nicht am 18.02... an diesem Datum werden sie erwischt. Ich denke wir als in der Zukunft lebende sind VERPFLICHTET dieses Wissen mit Sophie zu teilen, alles andere wäre unverantwortlich",
        "owner": {
          "id": "BS0N9xh6TPv53ZklNAmh9w==",
          "username": "Y2Vb8KfCWripB0Y2_19iJg=="
        },
        "likes_count": 2
      },
      {
        "id": 17884515116219512,
        "created_at": 1623684245,
        "text": "@Y2Vb8KfCWripB0Y2_19iJg== Es wird passieren, egal was du schreibst. Es tut einem leid für diese jungen Leute, aber genau die Geschehnisse des 18. Februar 1943 in München machen sie doch so bewundernswert. Ich habe extra München geschrieben, weil es am Abend diesen Tages in Berlin anders aussah (#giftzwerg #totalerkrieg)",
        "owner": {
          "id": "W_cWctkaUGyE670CzFanJQ==",
          "username": "PhcL3suZ7R1Wri6_Ndqrug=="
        },
        "likes_count": 0
      },
      {
        "id": 17870525591441226,
        "created_at": 1623685844,
        "text": "@Y2Vb8KfCWripB0Y2_19iJg== Das wird nachgespielt. Ich glaube kaum, dass einen Unterschied gemacht hätte, ob der Kalender 18.2.43, 5.5.43 oder sonst was zeigt. Der Schmid hätte sie auch an jedem anderen Tag erwischen können. Es war einfach ein Risiko, in die Uni zu gehen und zu tun was Hans und Sophie Scholl getan haben.",
        "owner": {
          "id": "W_cWctkaUGyE670CzFanJQ==",
          "username": "PhcL3suZ7R1Wri6_Ndqrug=="
        },
        "likes_count": 3
      }
    ]
  },
  {
    "id": 18157865407082984,
    "created_at": 1623670995,
    "text": "Cute sophie",
    "owner": {
      "id": "9x5uYbZyQKOhNqvM4idQMA==",
      "username": "C1d6atLhck9HYBOSeaY-ew=="
    },
    "likes_count": 1,
    "answers": []
  },
  {
    "id": 17869211330472254,
    "created_at": 1623668806,
    "text": "@hib4mKmHA-vgwtwb0Q_04A== Ich kann Doch so so gut verstehen. Ich hatte in den 90ern einen Lehrer, der noch immer sehr von der Überlegenheit der arischen Rasse überzeugt war und das versuchte mit Darwinismus zu begründen 🤯 Da ich damals schon Antifa war und ihm entsprechend Widerworte gegeben hab, flog ich regelmäßig raus 😔 Bis einmal mein Philosophielehrer ankam und mich fragte, wieso ich so traurig vor der Tür steh. Meine Erzählung hat ihn so wütend gemacht, dass er direkt zur Schulleitung ist und kurz darauf gab es einen neuen Bio-Lehrer 😊",
    "owner": {
      "id": "HSzpX1Kbd4-VICjri_Dwcw==",
      "username": "y3MgQQqFOnR4tBaRqt2dAg=="
    },
    "likes_count": 15,
    "answers": [
      {
        "id": 18176693935139858,
        "created_at": 1623690646,
        "text": "Ich habe es Anfang der 2000er Jahre als Mutter erlebt: mein Sohn kam eines Tages mit einigen Kapiteln des Buches \"Mein Kampf\" (Kopien) nach  Hause. Als ich es auf seinem Schreibtisch entdeckte und nachfragte meinte er sein Geschichtslehrer hat es verteilt und fände die Aussagen richtig. Wenn mensch danach handeln würde gab es in Berlin und ganz Deutschland keine Türken. Ich rief auf der Stelle den Rektor des Gymnasiums an und bat um ein Gespräch am nächsten Tag. Dieser Lehrer wurde darauf hin freigestellt. Komischerweise waren wir die einzigen Eltern, die darauf hinweisen und das Gespräch suchten.",
        "owner": {
          "id": "yyynItL9vewWH_OaTw1ByA==",
          "username": "ulv4i6u69STOK00-yCc8pA=="
        },
        "likes_count": 3
      },
      {
        "id": 17998966549338032,
        "created_at": 1623790465,
        "text": "Großartig. Dazu fällt mir ein: viele kleine Leute, an vielen kleinen Orten, die viele kleine Dinge tun, können das Gesicht der Welt verändern.",
        "owner": {
          "id": "m8q5jpoKMhEWDzLTSVd26Q==",
          "username": "yHryViefAi-JWWewnYKUeA=="
        },
        "likes_count": 0
      },
      {
        "id": 17911503859767932,
        "created_at": 1623668862,
        "text": "*Dich so gut verstehen",
        "owner": {
          "id": "HSzpX1Kbd4-VICjri_Dwcw==",
          "username": "y3MgQQqFOnR4tBaRqt2dAg=="
        },
        "likes_count": 2
      },
      {
        "id": 17904558511885291,
        "created_at": 1623682210,
        "text": "Noch in den 90ern? 🤭Das ist ja schrecklich. Respekt, dass du widersprochen hast.",
        "owner": {
          "id": "uXtwZD2eNBBcC8esoKutqQ==",
          "username": "62e7yDqldqc90BUQtt5ceA=="
        },
        "likes_count": 3
      },
      {
        "id": 17903805403979938,
        "created_at": 1623691913,
        "text": "@ulv4i6u69STOK00-yCc8pA== das ist unfassbar! Ehrlich gesagt, bei einem bekannteren (ehem) Geschichtslehrer, hätte mich das leiser nicht überrascht, aber das es evtl ein größeres Problem sein könnte…, darüber hätte ich jetzt nicht nachgedacht. Aber gut, dass ihr beide sofort gehandelt habt und es auch Konsequenzen hatte!",
        "owner": {
          "id": "g0S0BFRT87DeAL0axfu_ig==",
          "username": "t-tNgayJYb5RBy6dUpfWiA=="
        },
        "likes_count": 2
      }
    ]
  },
  {
    "id": 18234247432024591,
    "created_at": 1623668666,
    "text": "Ml",
    "owner": {
      "id": "DJsZcjBz6j5-cYKh4F0eOg==",
      "username": "TytfgjkQaAKzIjMXIlpHig=="
    },
    "likes_count": 1,
    "answers": []
  },
  {
    "id": 17887221173327583,
    "created_at": 1623668487,
    "text": "Wäre der Abbruch des Studiums nicht die Vermeidung deines frühen Todes gewesen?",
    "owner": {
      "id": "1SBGGYwAcX76eyqz8xDcwQ==",
      "username": "6_Q5ekB05KNXAIA9kyEuBQ=="
    },
    "likes_count": 0,
    "answers": []
  },
  {
    "id": 17857186799526115,
    "created_at": 1623668142,
    "text": "Feel it",
    "owner": {
      "id": "l1kY-tSr-TfnGf6xJi1cqw==",
      "username": "UPqbZJuFuts9dCQ_5l5XlQ=="
    },
    "likes_count": 1,
    "answers": []
  },
  {
    "id": 17913095260829391,
    "created_at": 1623667726,
    "text": "solche Vorlesungen kannst du vergessen. aber dafür hast du dort die richtigen Leute kennengelernt! konzentriere dich besser auf das, was dich wirklich weiterbringt.",
    "owner": {
      "id": "A6SPnLUgQz4dz87_9YRyig==",
      "username": "3Lri7y4IURwRCgPOV61qTg=="
    },
    "likes_count": 3,
    "answers": []
  },
  {
    "id": 17989714588361070,
    "created_at": 1623667647,
    "text": "Es ist immer wichtig, kritisch zu hinterfragen, über Werte und Meinungen zu diskutieren und sich verschiedene Quellen zur Meinungsbildung zu suchen. Das macht eine gewissenhafte Studentin aus! 👍",
    "owner": {
      "id": "ify18xh1e8ju9GsmxIKqtw==",
      "username": "4OeZsH6jQ-drWUSUsAls9g=="
    },
    "likes_count": 6,
    "answers": [
      {
        "id": 18187122559128531,
        "created_at": 1623672787,
        "text": "@4OeZsH6jQ-drWUSUsAls9g== das macht den gewissenhaften Menschen im Internetzeitalter aus.",
        "owner": {
          "id": "_olGnHo6y_Jl5CsMrerQeQ==",
          "username": "JJV-XcJ-rQj9Ldhqk_3DnA=="
        },
        "likes_count": 0
      }
    ]
  },
  {
    "id": 17888969042203154,
    "created_at": 1623666682,
    "text": "👏👏👏",
    "owner": {
      "id": "35JaI_7TFeEQYJu9gE5lgA==",
      "username": "9YCuJYBXhpUKXc6Ab8ptQg=="
    },
    "likes_count": 4,
    "answers": []
  },
  {
    "id": 17873531573383465,
    "created_at": 1623666452,
    "text": "Ohne dein Studium hättest du aber nicht Alex und Traute kennengelernt. Wenn du nicht weiterstudierst, was kommt dann?",
    "owner": {
      "id": "Sb5JgUdmtFsTY42RRW8JJg==",
      "username": "c72VVQQfTHBtpqKY4DQKFg=="
    },
    "likes_count": 31,
    "answers": [
      {
        "id": 17929779418597413,
        "created_at": 1623701708,
        "text": "@hib4mKmHA-vgwtwb0Q_04A==  is one of them playing a game on you think about this don't get mad or angry do all of your best I follow you 💯 from 🇨🇦 #YSW  bis spater aus kanada",
        "owner": {
          "id": "918nuwAFRG5kA1h2fSJICg==",
          "username": "YJLvwKucJceg07OdB2cYfw=="
        },
        "likes_count": 3
      },
      {
        "id": 17900887070021662,
        "created_at": 1623667964,
        "text": "@c72VVQQfTHBtpqKY4DQKFg== Ja das stimmt und darüber bin ich sehr dankbar! Eine wirkliche Alternative weiß ich gerade auch nicht, jedoch bereiten mir die Theorien, die uns hier gelehrt werden sollen langsam Bauchschmerzen...",
        "owner": {
          "id": "9rICyTfoSV8xPafAZ0Xo0w==",
          "username": "hib4mKmHA-vgwtwb0Q_04A=="
        },
        "likes_count": 57
      }
    ]
  },
  {
    "id": 17878725455320111,
    "created_at": 1623665708,
    "text": "Wie lange geht das Projekt? Wenn es in Echtzeit ist dann dauert es ja noch fast 3 Jahre bis die Geschichte von Sophie Scholl ein trauriges Ende nimmt",
    "owner": {
      "id": "FUZP5SGZe3aDzD1_2jPqWA==",
      "username": "kGhH83qc2gzWOie6LO4NQg=="
    },
    "likes_count": 8,
    "answers": [
      {
        "id": 17976472150381316,
        "created_at": 1623677629,
        "text": "@kGhH83qc2gzWOie6LO4NQg==  das verwechselst du mit Anne Frank. Sie starb 1945 kurz vor der Befreiung des KZ",
        "owner": {
          "id": "EfUELJF5lTeFoYQostoKZg==",
          "username": "fDeSAN0AMOQm_wnoqqcJJQ=="
        },
        "likes_count": 1
      },
      {
        "id": 17959536988442166,
        "created_at": 1623666951,
        "text": "@kGhH83qc2gzWOie6LO4NQg== Nein, leider ist Sophie am 22. Februar 1943 verstorben. Demnach geht dieses Projekt nur noch bis dahin...",
        "owner": {
          "id": "8PD9dL1d08QibYeHkTsAZA==",
          "username": "xMvnD61IgVIypzVUR8DL5Q=="
        },
        "likes_count": 20
      },
      {
        "id": 17920080817690027,
        "created_at": 1623670832,
        "text": "@JPv4W_1U5rrrXNU00N0bcg== wenn das dein Spoiler war dann mangelt es etwas an Allgemeinwissen...",
        "owner": {
          "id": "8PD9dL1d08QibYeHkTsAZA==",
          "username": "xMvnD61IgVIypzVUR8DL5Q=="
        },
        "likes_count": 5
      },
      {
        "id": 17906355874937270,
        "created_at": 1623667006,
        "text": "@_1gU1V8Dy67DMgIok1AR4w== oh okay :( ich dachte es sei kurz vor Kriegsende gewesen.\nDanke für die info!",
        "owner": {
          "id": "FUZP5SGZe3aDzD1_2jPqWA==",
          "username": "kGhH83qc2gzWOie6LO4NQg=="
        },
        "likes_count": 9
      },
      {
        "id": 17882656658340453,
        "created_at": 1623667022,
        "text": "@kGhH83qc2gzWOie6LO4NQg== Sophie erlebt das Ende des Krieges nicht. Im Februar 1943 (also in weniger als einem Jahr) werden sie und ihr Bruder beim Verteilen von Flugblättern im Lichthof der Universität entdeckt und verhaftet. Nur wenige Tage später, stehen sie vor dem Volksgerichtshof und noch am selben Tag wird das Urteil vollstreckt..",
        "owner": {
          "id": "WCvKFQOJZ9Nps46QU5naiw==",
          "username": "Fy-DLa3DTwl8nhY6R4Sr0A=="
        },
        "likes_count": 36
      },
      {
        "id": 17881737599279109,
        "created_at": 1623670271,
        "text": "@_1gU1V8Dy67DMgIok1AR4w== was'n spoiler.. :/",
        "owner": {
          "id": "WJMT2lFRfnLgv3bEFCRBMg==",
          "username": "JPv4W_1U5rrrXNU00N0bcg=="
        },
        "likes_count": 0
      },
      {
        "id": 17877686387466870,
        "created_at": 1623667658,
        "text": "@kGhH83qc2gzWOie6LO4NQg== #teamsoffer Das, was @naturheilduft_maren und @zuagroastebayrischeschwaebin sagen! Cool, dass ihr hier fleißig mit aufklärt. ❤️",
        "owner": {
          "id": "9rICyTfoSV8xPafAZ0Xo0w==",
          "username": "hib4mKmHA-vgwtwb0Q_04A=="
        },
        "likes_count": 58
      },
      {
        "id": 17871301493429553,
        "created_at": 1623671591,
        "text": "Ich finde dieses Projekt ,große Klasse.Gerade für die jüngere Generation.❤️",
        "owner": {
          "id": "zqp1sbwzA8ADZnrqeBrGdg==",
          "username": "2v6n2fKe40TDc7vWjM-pcQ=="
        },
        "likes_count": 4
      }
    ]
  },
  {
    "id": 17897823758085021,
    "created_at": 1623665462,
    "text": "Wie Verdiente sie ihr Geld für Wohnung etc.?",
    "owner": {
      "id": "n9cZpM5Pc6z_BxBfYCsHWw==",
      "username": "0DPerngRxvweXIvwSxxFEA=="
    },
    "likes_count": 2,
    "answers": []
  },
  {
    "id": 17867008643488908,
    "created_at": 1623665296,
    "text": "Wieso ist Insta im dritten Reich nicht zensiert 🙈",
    "owner": {
      "id": "StbpcTBNDJUq8CUkCDlTRQ==",
      "username": "xZZRrwku_Rjp_ZiRFHd7tQ=="
    },
    "likes_count": 0,
    "answers": []
  },
  {
    "id": 17919343816698043,
    "created_at": 1623664817,
    "text": "Ich habe gehört, dass man in den Städten mittlerweile ganz schlecht an frisches Obst und Gemüse kommt bzw die Lebensmittelversorgung allgemein ein immer deutlicheres Problem wird… bist Du noch gut versorgt?",
    "owner": {
      "id": "WCvKFQOJZ9Nps46QU5naiw==",
      "username": "Fy-DLa3DTwl8nhY6R4Sr0A=="
    },
    "likes_count": 8,
    "answers": [
      {
        "id": 18164454610148823,
        "created_at": 1623691902,
        "text": "@AEnUymL0-C3D-6VwXS3GYw== gern doch 😊",
        "owner": {
          "id": "ify18xh1e8ju9GsmxIKqtw==",
          "username": "4OeZsH6jQ-drWUSUsAls9g=="
        },
        "likes_count": 2
      },
      {
        "id": 18154763269197986,
        "created_at": 1623668270,
        "text": "@AEnUymL0-C3D-6VwXS3GYw== #teamsoffer \n1942 waren Lebensmittel und andere Konsumgüter nur umständlich verfügbar. Um sie zu erwerben benötigte man (Lebensmittel-) Marken. Es gab in Deutschland zu diesem Zeitpunkt dennoch keine schwerwiegende Lebensmittelknappheit.",
        "owner": {
          "id": "9rICyTfoSV8xPafAZ0Xo0w==",
          "username": "hib4mKmHA-vgwtwb0Q_04A=="
        },
        "likes_count": 7
      },
      {
        "id": 17936956588526719,
        "created_at": 1623670176,
        "text": "@hib4mKmHA-vgwtwb0Q_04A== oh, das ist mir jetzt peinlich🙈 - ich hatte am WE n bisschen recherchiert und n bisschen was zu den Briefen gefunden und fand es so auffällig, dass die ganze Zeit über Lebensmittel und die Bitten etwas zu schicken geschrieben wurde (über alles möglich, aber vor allem über frische Lebensmittel und auch ganz, ganz oft über Butter - wo ich mich dann auch gefragt habe, wie man wohl Butter verschickt hat..😅). Aber man konnte ja nicht wirklich schreiben, was gerade los ist.. evtl war das ja ein Code für irgendwas oder der Eindruck war verzerrt weil ich in frei zugänglichen Quellen natürlich nur kurze Ausschnitte der Briefe fand. Evtl warte ich noch das Buch zu den Schriftwechseln ab, dass ich mir bestellt habe☺️",
        "owner": {
          "id": "WCvKFQOJZ9Nps46QU5naiw==",
          "username": "Fy-DLa3DTwl8nhY6R4Sr0A=="
        },
        "likes_count": 3
      },
      {
        "id": 17900814826949256,
        "created_at": 1623691325,
        "text": "@4OeZsH6jQ-drWUSUsAls9g== ach wirklich? Da war ich schon so oft, aber das wusste ich nicht! Herzlichen Dank für Info!",
        "owner": {
          "id": "WCvKFQOJZ9Nps46QU5naiw==",
          "username": "Fy-DLa3DTwl8nhY6R4Sr0A=="
        },
        "likes_count": 2
      },
      {
        "id": 17870689052445123,
        "created_at": 1623683756,
        "text": "@AEnUymL0-C3D-6VwXS3GYw== das MilchHäusl im Englischen Garten war übrigens dieser Ausgabestellen für Essen und Getränke, daher auch der Name 😊",
        "owner": {
          "id": "ify18xh1e8ju9GsmxIKqtw==",
          "username": "4OeZsH6jQ-drWUSUsAls9g=="
        },
        "likes_count": 4
      }
    ]
  },
  {
    "id": 17899460108046540,
    "created_at": 1623662621,
    "text": "Blöd ist nur, dass Fragen gefährlich sein können…",
    "owner": {
      "id": "SZxPct385NdxCWQJVB8_UQ==",
      "username": "NX_aRRylTqr94Mt5McbnEQ=="
    },
    "likes_count": 2,
    "answers": []
  },
  {
    "id": 18183675340114470,
    "created_at": 1623662261,
    "text": "Wie fühlst du dich?",
    "owner": {
      "id": "7T-WqDsn7S3FaZv7zh2Z0g==",
      "username": "H47ZTlxQpdt1nNFuHcEiHw=="
    },
    "likes_count": 4,
    "answers": [
      {
        "id": 17931771241565957,
        "created_at": 1623663913,
        "text": "@H47ZTlxQpdt1nNFuHcEiHw== Ich habe Wut im Bauch über die Theorien, die uns hier gelehrt werden sollen...",
        "owner": {
          "id": "9rICyTfoSV8xPafAZ0Xo0w==",
          "username": "hib4mKmHA-vgwtwb0Q_04A=="
        },
        "likes_count": 19
      }
    ]
  },
  {
    "id": 17874775070355858,
    "created_at": 1623662193,
    "text": "Ja scheiss auf Studium digga",
    "owner": {
      "id": "KTmQ9gJaX-2y4BXOqkpCvw==",
      "username": "OczQSV_jyhLpZJpAIdxS2w=="
    },
    "likes_count": 1,
    "answers": []
  },
  {
    "id": 18169322230135916,
    "created_at": 1623662067,
    "text": "Vielleicht weil du immernoch Hoffnung hast und du durch die schöne Zeit in der Natur, diese Nazi lehren ein Stück vergessen konntest. Bleib einfach im Austausch mit deinen Freunden, du weist ja zusammen seit ihr Stark 💪. Heute fängt bei mir eine Schnupperwoche im Theologie Studium an und ich bin gespannt was mich da so erwartet. Gott ist an meiner seite und das möchte ich dir auch mitgeben 🙏 #ichbinsophiescholl",
    "owner": {
      "id": "EetyMbDY3uCSUXWqH6mKyg==",
      "username": "pKP0Ou_N-bD7Hz3c9RR35w=="
    },
    "likes_count": 2,
    "answers": []
  },
  {
    "id": 17931678064528092,
    "created_at": 1623661570,
    "text": "Ernste Zeit ernster Blick",
    "owner": {
      "id": "VH1mamEzS0BYvKuNI9IGnw==",
      "username": "kjmJsSBlfGxYdnX_GBzVDA=="
    },
    "likes_count": 3,
    "answers": []
  },
  {
    "id": 17911769089759067,
    "created_at": 1623661370,
    "text": "So beauty❤️❤️❤️",
    "owner": {
      "id": "zZAFVEx4D9ZZl0b3LJ8ZIg==",
      "username": "51CrkDqktUh8FZ-UgztoSA=="
    },
    "likes_count": 0,
    "answers": []
  },
  {
    "id": 17889048716201519,
    "created_at": 1623660424,
    "text": "Kann man das auch irgendwo schauen? Oder ist es nur rein auf Instagram?",
    "owner": {
      "id": "5jv9u4uO4J1QyagEsNhzHQ==",
      "username": "kKS6gflFflgkOdfvtEUMCA=="
    },
    "likes_count": 6,
    "answers": [
      {
        "id": 17972246107396808,
        "created_at": 1623664512,
        "text": "@hib4mKmHA-vgwtwb0Q_04A== super dann habe ich nichts verpasst ich finde es sehr interessant wie es früher war und sehr authentisch",
        "owner": {
          "id": "5jv9u4uO4J1QyagEsNhzHQ==",
          "username": "kKS6gflFflgkOdfvtEUMCA=="
        },
        "likes_count": 3
      },
      {
        "id": 17950698718464300,
        "created_at": 1623667481,
        "text": "@hib4mKmHA-vgwtwb0Q_04A== Das sollte nach Ende der Laufzeit unbedingt in andere Sprachen übersetzt werden und für Bildungseinrichtungen auf Blu-ray verfügbar sein.",
        "owner": {
          "id": "Y6qAl__GnQvnC07MKvmnBA==",
          "username": "TZ7Tf34VN8R_KEg8VD37MQ=="
        },
        "likes_count": 16
      },
      {
        "id": 17930306794601136,
        "created_at": 1623664095,
        "text": "@kKS6gflFflgkOdfvtEUMCA== #teamsoffer Das Projekt @ichbinsophiescholl wird lediglich auf diesem Account ausgespielt. Liebe Grüße :)",
        "owner": {
          "id": "9rICyTfoSV8xPafAZ0Xo0w==",
          "username": "hib4mKmHA-vgwtwb0Q_04A=="
        },
        "likes_count": 25
      },
      {
        "id": 17929475611600026,
        "created_at": 1623679482,
        "text": "@BOx7QD6JVyPG4YozWN6VLQ== Bliebe nur die Frage, ob das dann auch der geschichtskulturellen Idee hinter dem Projekt entspräche.",
        "owner": {
          "id": "7MwbIOHXcqEF3zGGp_S0hA==",
          "username": "EDXUd4fq1-uAN0Tooi9m_Q=="
        },
        "likes_count": 2
      }
    ]
  },
  {
    "id": 17849398172601919,
    "created_at": 1623660260,
    "text": "Immer wenn ich das lese kommt so viel Wut in mir auf. So viel unglücklichkeit das es immer noch Menschen gibt die diese Theorien unterschreiben würden.",
    "owner": {
      "id": "s4C1sn7eBUecBytvTHpTEg==",
      "username": "4EqywgzTs6qUbhpRhfaWXg=="
    },
    "likes_count": 2,
    "answers": []
  },
  {
    "id": 17887163951176224,
    "created_at": 1623660090,
    "text": "Ihr habt hier echt ein mega Projekt auf die Beine gestellt! Wann wurden denn die ganzen Szenen in der Uni gedreht? Kann mir vorstellen, dass es sicher ein sehr seltsames Gefühl war, überall diese Flaggen aufzuhängen. Allerdings seh ich immerhin so mal wieder was vom Inneren der Uni 🙈😅",
    "owner": {
      "id": "5RkceR4Gm4yEPCKxBSpb4A==",
      "username": "coDe2Z8UVJX9lUhQga0X0g=="
    },
    "likes_count": 36,
    "answers": [
      {
        "id": 17926193611627684,
        "created_at": 1623687117,
        "text": "@coDe2Z8UVJX9lUhQga0X0g== welche Uni ist das denn? 🙈",
        "owner": {
          "id": "ceYXIHnHpM__gW5HOmi_Cw==",
          "username": "4v7BOOBoVBtUmy-CgmMQjw=="
        },
        "likes_count": 1
      },
      {
        "id": 17917300360738841,
        "created_at": 1623681686,
        "text": "@tI0avYqp8qp_SbYpSer1ow== hab’s nur 1x gesehen, hab im Oktober das Studium angefangen 😂 irgendwann vor 2 Jahren oder so war ich mal kurz drinnen und hab auch die Gedenkstätte und die Ausstellung besucht. Einen Hörsaal hab ich hier aber noch nie von innen gesehen 😅",
        "owner": {
          "id": "5RkceR4Gm4yEPCKxBSpb4A==",
          "username": "coDe2Z8UVJX9lUhQga0X0g=="
        },
        "likes_count": 2
      },
      {
        "id": 17900218529048809,
        "created_at": 1623687304,
        "text": "@4v7BOOBoVBtUmy-CgmMQjw== das ist die LMU in München 😊",
        "owner": {
          "id": "5RkceR4Gm4yEPCKxBSpb4A==",
          "username": "coDe2Z8UVJX9lUhQga0X0g=="
        },
        "likes_count": 2
      },
      {
        "id": 17897470010083072,
        "created_at": 1623671775,
        "text": "@coDe2Z8UVJX9lUhQga0X0g== Geht mir genauso 😅 seit Über einem Jahr das Gebäude nicht von innen gesehen 😂",
        "owner": {
          "id": "aOYeooZf3dK3GR4kvOCeYg==",
          "username": "1-DKtHhTFHQ04EljYP76Qw=="
        },
        "likes_count": 2
      },
      {
        "id": 17887138715322974,
        "created_at": 1623681612,
        "text": "@lCKLuKni8uNdNKEqQwACSA== das ist mir wohl bewusst, trotzdem ist es kein alltäglicher Anblick…",
        "owner": {
          "id": "5RkceR4Gm4yEPCKxBSpb4A==",
          "username": "coDe2Z8UVJX9lUhQga0X0g=="
        },
        "likes_count": 2
      },
      {
        "id": 17869160633469423,
        "created_at": 1623681454,
        "text": "@coDe2Z8UVJX9lUhQga0X0g== die Uni hat schon für so viele Filme Hakenkreuzflaggen „gesehen“…",
        "owner": {
          "id": "8VkPq5VosORoJPR59TLHuw==",
          "username": "lCKLuKni8uNdNKEqQwACSA=="
        },
        "likes_count": 1
      }
    ]
  },
  {
    "id": 17925503731628232,
    "created_at": 1623660041,
    "text": "Ein Studium besteht nicht darin, Theorien zu folgen, sondern zu lernen das \"Richtige\" zu lernen und dieses vom \"Falschen\" zu unterscheiden. Mache weiter mit dem Studium, versuche weiterhin auch verbotene Literatur trotzdem zu lesen und setzte dich kritisch mit all dem was du in den Vorlesungen konfrontiert wirst auseinander. Vor allem aber: Versuche diesen höllischen Krieg zu überleben den die Allierten mit Sicherheit gewinnen werden. Deutschland braucht danach kluge Köpfe um eine stabile Demokratie aufzubauen. Du solltest dazugehören! Bleib übrig 😍",
    "owner": {
      "id": "mA2-qy_WCKZaYBve_b0Brg==",
      "username": "wCEgABSHkmoNXgZ4Co1_Zw=="
    },
    "likes_count": 9,
    "answers": []
  },
  {
    "id": 17909091421821179,
    "created_at": 1623659866,
    "text": "😢",
    "owner": {
      "id": "6PdHaeR5CDE-QLKnchA3PA==",
      "username": "2873NKgl-fK6JTWMKz5v4A=="
    },
    "likes_count": 3,
    "answers": []
  },
  {
    "id": 17960460346432134,
    "created_at": 1623659693,
    "text": "Kann ich gut nachvollziehen! Denken vs. Wissen...auch ich habe mich das WE mit der Vergangenheit Deutschlands beschäftigt...unverheiratete Frauen, die unehelich schwanger wurden, Sterilisierung, ja, der Rassenwahn der Nazis, \"unwertvolles Leben\" etc. Es ist verdammt bedrückend, doch jetzt verstehe ich meine eigene (Familien) Geschichte mener weiblichen Linie besser! Das ich überhaupt hier bin, da kann ich wirklich nur einem \"guten\" Deutschen dankbar sein, der mitdachte und wusste recht von schlecht! Danke :-)",
    "owner": {
      "id": "Q7HxCluTAXPfY0rqo9wB3Q==",
      "username": "lAgSFEtIPxxY5vbH9SPLtw=="
    },
    "likes_count": 2,
    "answers": []
  },
  {
    "id": 18157344898081830,
    "created_at": 1623659509,
    "text": "Kann ich gut nachvollziehen! Denken vs. Wissen...auch ich habe mich das WE mit der Vergangenheit Deutschlands beschäftigt...unverheiratete Frauen, die unehelich schwanger wurden, Sterilisierung, ja, der Rassenwahn der Nazis, \"unwertvolles Leben\" etc. Es ist verdammt bedrückend, doch jetzt verstehe ich meine eigene (Familien) Geschichte mener weiblichen Linie besser! Das ich überhaupt hier bin, da kann ich wirklich nur einem \"guten\" Deutschen dankbar sein, der mitdachte und wusste recht von schlecht! Danke :-)",
    "owner": {
      "id": "Q7HxCluTAXPfY0rqo9wB3Q==",
      "username": "lAgSFEtIPxxY5vbH9SPLtw=="
    },
    "likes_count": 4,
    "answers": []
  },
  {
    "id": 17892144752084223,
    "created_at": 1623659188,
    "text": "Du lernst, zu hinterfragen und selbst zu denken. Das ist in jeder Zeit unbezahlbar! Ich wünschte, du könntest unter anderen Bedingungen wachsen, liebe Sophie.",
    "owner": {
      "id": "i418nFbk6ty85K-B0tpk5Q==",
      "username": "WTP1qBmCXXgus-BgBYUrNg=="
    },
    "likes_count": 62,
    "answers": []
  },
  {
    "id": 17899859735029197,
    "created_at": 1623659108,
    "text": "Du lernst, zu hinterfragen und selbst zu denken. Das ist in jeder Zeit unbezahlbar! Ich wünschte, du könntest unter anderen Bedingungen wachsen, liebe Sophie.",
    "owner": {
      "id": "i418nFbk6ty85K-B0tpk5Q==",
      "username": "WTP1qBmCXXgus-BgBYUrNg=="
    },
    "likes_count": 23,
    "answers": []
  },
  {
    "id": 17918973619694791,
    "created_at": 1623658891,
    "text": "Immer wenn ich das lese kommt so viel Wut in mir auf. So viel unglücklichkeit das es immer noch Menschen gibt die diese Theorien unterschreiben würden.",
    "owner": {
      "id": "s4C1sn7eBUecBytvTHpTEg==",
      "username": "4EqywgzTs6qUbhpRhfaWXg=="
    },
    "likes_count": 1,
    "answers": []
  },
  {
    "id": 17889410999284536,
    "created_at": 1623658834,
    "text": "Nur kurz um das einordnen zu können, welches Jahr ist gerade?",
    "owner": {
      "id": "4TSHdPeozcMjKqJlPnfYJQ==",
      "username": "Mwr70J8NhwB4KhIQ4q5fzQ=="
    },
    "likes_count": 51,
    "answers": [
      {
        "id": 18131217034201951,
        "created_at": 1623742384,
        "text": "@PvoekaiQ6NO8t5qP-tZ-Tg== Stimmt schon. Wo du Recht hast, hast du Recht. ☺",
        "owner": {
          "id": "M7-8tlVbI8GuU8-MthS32g==",
          "username": "XMlTchMyxPYWKAgy-13-Hw=="
        },
        "likes_count": 0
      },
      {
        "id": 17998439791338267,
        "created_at": 1623659052,
        "text": "@a9uTgtx4rfMABZ-rf9pc4w== danke :)",
        "owner": {
          "id": "4TSHdPeozcMjKqJlPnfYJQ==",
          "username": "Mwr70J8NhwB4KhIQ4q5fzQ=="
        },
        "likes_count": 2
      },
      {
        "id": 17946833572482630,
        "created_at": 1623659016,
        "text": "@Mwr70J8NhwB4KhIQ4q5fzQ== 1942 müsste es sein",
        "owner": {
          "id": "JnVoFrQpry_WysoYK9_Uvg==",
          "username": "a9uTgtx4rfMABZ-rf9pc4w=="
        },
        "likes_count": 4
      },
      {
        "id": 17931507814538352,
        "created_at": 1623669406,
        "text": "@hib4mKmHA-vgwtwb0Q_04A== Uni an einem Sonntag?",
        "owner": {
          "id": "M7-8tlVbI8GuU8-MthS32g==",
          "username": "XMlTchMyxPYWKAgy-13-Hw=="
        },
        "likes_count": 0
      },
      {
        "id": 17902057912993203,
        "created_at": 1623671903,
        "text": "@Pv6R1x_R-qlkXhKGZ3FAHg== alles klar danke",
        "owner": {
          "id": "iUF500eiqY1wHQrEBebnFQ==",
          "username": "oHtpWF4QM_JSiDoRbbepBQ=="
        },
        "likes_count": 1
      },
      {
        "id": 17894688242137197,
        "created_at": 1623672492,
        "text": "@oHtpWF4QM_JSiDoRbbepBQ== Doch war es. Habe nachgeschaut. Einfach mal \"Kalender 1942\" googeln.",
        "owner": {
          "id": "M7-8tlVbI8GuU8-MthS32g==",
          "username": "XMlTchMyxPYWKAgy-13-Hw=="
        },
        "likes_count": 0
      },
      {
        "id": 17888883203283966,
        "created_at": 1623659975,
        "text": "@Mwr70J8NhwB4KhIQ4q5fzQ== 2021",
        "owner": {
          "id": "dcjLd1OxJK3n0RMZ8qrszg==",
          "username": "BrUvgfbH0TEP2nwxkKt6aA=="
        },
        "likes_count": 3
      },
      {
        "id": 17888780075276662,
        "created_at": 1623659191,
        "text": "@a9uTgtx4rfMABZ-rf9pc4w== #teamsoffer richtig! Es ist der 14.06.1942 🙂",
        "owner": {
          "id": "9rICyTfoSV8xPafAZ0Xo0w==",
          "username": "hib4mKmHA-vgwtwb0Q_04A=="
        },
        "likes_count": 160
      },
      {
        "id": 17884426778222690,
        "created_at": 1623670549,
        "text": "@XMlTchMyxPYWKAgy-13-Hw== vielleicht war es am 14.06.1942 kein Sonntag",
        "owner": {
          "id": "iUF500eiqY1wHQrEBebnFQ==",
          "username": "oHtpWF4QM_JSiDoRbbepBQ=="
        },
        "likes_count": 0
      }
    ]
  },
  {
    "id": 17922672157716763,
    "created_at": 1623658818,
    "text": "❤️❤️❤️❤️❤️❤️",
    "owner": {
      "id": "ErR67EvMU3Fo4IC4lqqNWA==",
      "username": "YAffeJ37OZSHglZgXwX1Hg=="
    },
    "likes_count": 7,
    "answers": []
  },
  {
    "id": 17893271420168406,
    "created_at": 1623658687,
    "text": "Austausch mit gleichgesinnten ist so wichtig 👏❤️",
    "owner": {
      "id": "V2NKwSLFhB3Z-U9NfcCt2w==",
      "username": "4vc7_ZCRZc0W_sK7IJB-JA=="
    },
    "likes_count": 2,
    "answers": []
  },
  {
    "id": 17881060055366020,
    "created_at": 1623658264,
    "text": "Austausch mit gleichgesinnten ist so wichtig 👏❤️",
    "owner": {
      "id": "V2NKwSLFhB3Z-U9NfcCt2w==",
      "username": "4vc7_ZCRZc0W_sK7IJB-JA=="
    },
    "likes_count": 18,
    "answers": [
      {
        "id": 17895210314135793,
        "created_at": 1623658941,
        "text": "@4vc7_ZCRZc0W_sK7IJB-JA== Oder so fatal...",
        "owner": {
          "id": "JA7kbqr1oXjRoNZWCQ52bA==",
          "username": "KlKDY4o3kKbsWQmG3QTwJA=="
        },
        "likes_count": 8
      }
    ]
  },
  {
    "id": 17902161913997343,
    "created_at": 1623658128,
    "text": "😍",
    "owner": {
      "id": "7n1aBMPlb49b3vwuxnCXrg==",
      "username": "e1Grf44soeXLBuIGYrjndw=="
    },
    "likes_count": 4,
    "answers": []
  },
  {
    "id": 17878595279469158,
    "created_at": 1623657764,
    "text": "Rilke kann immer empfohlen werden.",
    "owner": {
      "id": "xju5iXkEjx4gw0_mcyAT5A==",
      "username": "39NBL2vW0CxNHsXkou-6QA=="
    },
    "likes_count": 7,
    "answers": []
  },
  {
    "id": 17936847352534365,
    "created_at": 1623657746,
    "text": "Kann ich verstehen. Dieses Thema hat mich in der Schule auch immer runter gezogen.",
    "owner": {
      "id": "0JGy1vW9l58a9uf5oEdpLw==",
      "username": "kaLhFxgcO_vBDDvxpYIEDw=="
    },
    "likes_count": 7,
    "answers": []
  },
  {
    "id": 17925852874621681,
    "created_at": 1623657727,
    "text": "Kann ich verstehen. Dieses Thema hat mich in der Schule auch immer runter gezogen.",
    "owner": {
      "id": "0JGy1vW9l58a9uf5oEdpLw==",
      "username": "kaLhFxgcO_vBDDvxpYIEDw=="
    },
    "likes_count": 2,
    "answers": []
  },
  {
    "id": 17993866831352598,
    "created_at": 1623657422,
    "text": "Das ist bestimmt eine ganz dumme Frage, aber warum war dein Bruder und Hans nicht an der Front ?",
    "owner": {
      "id": "m_78DNLO-MLn1gQHdzzHZA==",
      "username": "Np99B7Oos1HFaCVwRCjrYg=="
    },
    "likes_count": 47,
    "answers": [
      {
        "id": 17943286219474463,
        "created_at": 1623657795,
        "text": "@Np99B7Oos1HFaCVwRCjrYg== #teamsoffer Als Studenten mussten sie während des Semesters erst einmal nicht an die Front. Während der Semesterferien arbeitete Hans aber als Sanitäter im Frontdienst und wurde dann im Juli 1942 mit Alex zusammen zum Einsatz an der Ostfront eingezogen.",
        "owner": {
          "id": "9rICyTfoSV8xPafAZ0Xo0w==",
          "username": "hib4mKmHA-vgwtwb0Q_04A=="
        },
        "likes_count": 180
      },
      {
        "id": 17911023238855757,
        "created_at": 1623661200,
        "text": "@hib4mKmHA-vgwtwb0Q_04A== danke für die schnelle Antwort 💡",
        "owner": {
          "id": "m_78DNLO-MLn1gQHdzzHZA==",
          "username": "Np99B7Oos1HFaCVwRCjrYg=="
        },
        "likes_count": 2
      }
    ]
  },
  {
    "id": 17945186785496157,
    "created_at": 1623657376,
    "text": "Was sind das für Theorien? Gibts dazu Literatur, was damals unterrichtet wurde? Habe selbst Biologie studiert und ich fände das echt interessant 😊",
    "owner": {
      "id": "kJHDAfklrvSKVEb51ZhuRA==",
      "username": "Ga3J5rhNOCYA9PVaheTdsg=="
    },
    "likes_count": 13,
    "answers": [
      {
        "id": 17923343431646108,
        "created_at": 1623696498,
        "text": "@Ga3J5rhNOCYA9PVaheTdsg== Eugenik beruhte auf den Sozialdarwinismus und der wiederum,beruhte auf den Darwinismus. Das war alles nichts Neues. Vor allem das Buch \"Versuch über den Ungleichhei der Menschenrassen\" von Gobineau hat die nationalsozialistische Ideologie sehr geprägt.",
        "owner": {
          "id": "s-wogNZkRfvdMJHcFFB16A==",
          "username": "gQ56qBofHsrGEae5j3pu3g=="
        },
        "likes_count": 0
      },
      {
        "id": 17911755790766021,
        "created_at": 1623679971,
        "text": "@Ga3J5rhNOCYA9PVaheTdsg== Es gibt Veröffentlichungen z. B. der Biologiehistorikerin Änne Bäumer zur Politisierung der Biologie in der NS-Zeit. Ist allerdings schon von 1989, evtl. gibts was neueres. :)",
        "owner": {
          "id": "BgHwq7d7GwT4br6aRwD6iA==",
          "username": "J73HYFZEN1cUbwDvddKTIQ=="
        },
        "likes_count": 1
      },
      {
        "id": 17910906049777552,
        "created_at": 1623661577,
        "text": "@Ga3J5rhNOCYA9PVaheTdsg== ich weiß es nicht genau aber soweit ich weiß wurden Theorien nicht \"wissenschaftlich\" erklärt. Sie wurden nur mit willkürlicher pseudo Wissenschaft begründet.",
        "owner": {
          "id": "-NT2UFF33hi61LrG61D1KA==",
          "username": "BQGgYkZECgAv0X3NwfdJiA=="
        },
        "likes_count": 1
      },
      {
        "id": 17900077535032630,
        "created_at": 1623659762,
        "text": "@8-bCeBe9N19ep9O_bMSH7g==  ich meinte eigentlich was genau in der Zeit unterrichtet wurde..also nicht nur Rassenlehre, sondern auch wie sie \"wissenschaftlich\" begründet wurde 😊",
        "owner": {
          "id": "kJHDAfklrvSKVEb51ZhuRA==",
          "username": "Ga3J5rhNOCYA9PVaheTdsg=="
        },
        "likes_count": 6
      }
    ]
  },
  {
    "id": 17966488783416145,
    "created_at": 1623657200,
    "text": "Unterdessen in Amsterdam: Am 14.6.1942 schrieb Anne Frank den ersten Eintrag in ihr Tagebuch. Sie beschreibt darin ihren Geburtstag am 12.6., zu dem sie u.a. das besagte Tagebuch geschenkt bekommen hatte. Dann war sie wie jeden Tag zur Schule gegangen, und weil es ihr Geburtstag war, hatte sie eine Runde Butterplätzchen für alle mitgebracht.",
    "owner": {
      "id": "_-mf1Sd6sDCg_OX_PGE1gA==",
      "username": "7bpYHV7nhElkgQTPROvDQg=="
    },
    "likes_count": 421,
    "answers": [
      {
        "id": 18170691166135998,
        "created_at": 1623671323,
        "text": "@AEnUymL0-C3D-6VwXS3GYw== Danke für den Tipp. 🙋🏼‍♀️",
        "owner": {
          "id": "kaE8RVaJC8GOJmDgx-q6ug==",
          "username": "lt6PZDnca-0itoPXXN11PQ=="
        },
        "likes_count": 3
      },
      {
        "id": 18121172458226309,
        "created_at": 1623667482,
        "text": "@lt6PZDnca-0itoPXXN11PQ== ich glaube zu Anne Frank gibt es ein ähnliches Projekt des Anne Frank Hauses auf YouTube.",
        "owner": {
          "id": "WCvKFQOJZ9Nps46QU5naiw==",
          "username": "Fy-DLa3DTwl8nhY6R4Sr0A=="
        },
        "likes_count": 8
      },
      {
        "id": 17938628620499700,
        "created_at": 1623657326,
        "text": "@7bpYHV7nhElkgQTPROvDQg== (Der 14.6.1942 war übrigens ein Sonntag).",
        "owner": {
          "id": "_-mf1Sd6sDCg_OX_PGE1gA==",
          "username": "7bpYHV7nhElkgQTPROvDQg=="
        },
        "likes_count": 17
      },
      {
        "id": 17930358604581230,
        "created_at": 1623684002,
        "text": "@PhcL3suZ7R1Wri6_Ndqrug== Das kann ich verstehen. Es ist wichtig, da achtsam mit sich selbst umzugehen.",
        "owner": {
          "id": "_-mf1Sd6sDCg_OX_PGE1gA==",
          "username": "7bpYHV7nhElkgQTPROvDQg=="
        },
        "likes_count": 3
      },
      {
        "id": 17912902135804530,
        "created_at": 1623690427,
        "text": "@7bpYHV7nhElkgQTPROvDQg== wo kann ich denn  zu Anne Frank parallel mit lesen? Eine furchtbare Zeit die zwei so starke Frauen hervor brachte....",
        "owner": {
          "id": "Oa16Bpg2Eqs9erp5SroV9g==",
          "username": "4OSc4JBIQJZLhRnbj-p_bQ=="
        },
        "likes_count": 2
      },
      {
        "id": 17909566189803832,
        "created_at": 1623669682,
        "text": "@7bpYHV7nhElkgQTPROvDQg== uns hast du dazu auf jeden Fall animiert 😁",
        "owner": {
          "id": "ify18xh1e8ju9GsmxIKqtw==",
          "username": "4OeZsH6jQ-drWUSUsAls9g=="
        },
        "likes_count": 5
      },
      {
        "id": 17907124354916691,
        "created_at": 1623668779,
        "text": "@7bpYHV7nhElkgQTPROvDQg== vielleicht machen sie soetwas auch mal mit Anne Frank!  Wäre toll!!",
        "owner": {
          "id": "H1ZKlqSpoRDpBlo2-X86Tw==",
          "username": "TRyr3KP5OQisqInymiPiUA=="
        },
        "likes_count": 4
      },
      {
        "id": 17906450677937736,
        "created_at": 1623661215,
        "text": "@7bpYHV7nhElkgQTPROvDQg== Danke. Das alles berührt mich sehr.",
        "owner": {
          "id": "-gKiIZee7yFe6J6R5MlaiA==",
          "username": "YZ3HpLUP33aKbFJEKeIYkg=="
        },
        "likes_count": 11
      },
      {
        "id": 17902158950006735,
        "created_at": 1623659139,
        "text": "@7bpYHV7nhElkgQTPROvDQg== danke für den Kontext;",
        "owner": {
          "id": "HJjBr9l7M72oIIIk35AHTg==",
          "username": "panmnpe4CawIrC_9CPwRHg=="
        },
        "likes_count": 13
      },
      {
        "id": 17902010815899553,
        "created_at": 1623664597,
        "text": "@7bpYHV7nhElkgQTPROvDQg== An Anne Frank habe ich auch schon oft gedacht. Den Menschen ihr Leben über einen solchen Account wie diesen nahe zu bringen, wäre bestimmt auch eine tolle Sache. Da ja dieser Account und diese Art des Geschichtenerzählens so unglaublich gut ankommt, bekommen vielleicht auch noch andere Menschen eine derartige Würdigung für ihr Leben und ihr Tun. Danke für den Hinweis auf Anne Frank. 😍",
        "owner": {
          "id": "kaE8RVaJC8GOJmDgx-q6ug==",
          "username": "lt6PZDnca-0itoPXXN11PQ=="
        },
        "likes_count": 51
      },
      {
        "id": 17899381405976816,
        "created_at": 1623694758,
        "text": "@7bpYHV7nhElkgQTPROvDQg== ah, gut, dachte es gäbe das vielleicht auch in so einer Form, aber das Tagebuch ergibt natürlich sinn",
        "owner": {
          "id": "Oa16Bpg2Eqs9erp5SroV9g==",
          "username": "4OSc4JBIQJZLhRnbj-p_bQ=="
        },
        "likes_count": 3
      },
      {
        "id": 17887302518168030,
        "created_at": 1623684345,
        "text": "@7bpYHV7nhElkgQTPROvDQg== Ich habe mich viel mit dem Gesamten beschäftigt und komme irgendwie nicht davon los.",
        "owner": {
          "id": "W_cWctkaUGyE670CzFanJQ==",
          "username": "PhcL3suZ7R1Wri6_Ndqrug=="
        },
        "likes_count": 3
      },
      {
        "id": 17882224925274296,
        "created_at": 1623667571,
        "text": "@7bpYHV7nhElkgQTPROvDQg== danke für die Antwort. Diese parallele Entwicklung könnte wirklich sehr spannend sein",
        "owner": {
          "id": "ify18xh1e8ju9GsmxIKqtw==",
          "username": "4OeZsH6jQ-drWUSUsAls9g=="
        },
        "likes_count": 7
      },
      {
        "id": 17872092476418094,
        "created_at": 1623667690,
        "text": "@4OeZsH6jQ-drWUSUsAls9g== Ich will diesen Account nicht kapern, aber vielleicht animiert es den einen oder die andere, parallel mitzulesen?",
        "owner": {
          "id": "_-mf1Sd6sDCg_OX_PGE1gA==",
          "username": "7bpYHV7nhElkgQTPROvDQg=="
        },
        "likes_count": 14
      },
      {
        "id": 17857447604566930,
        "created_at": 1623692858,
        "text": "@4OSc4JBIQJZLhRnbj-p_bQ== Vielleicht im Tagebuch selbst,  so als Offline-Content nebenher? (Ich glaube, online steht leider nur das niederländische Original; die deutsche Übersetzung könnte noch urheberrechtlich geschützt sein.)",
        "owner": {
          "id": "_-mf1Sd6sDCg_OX_PGE1gA==",
          "username": "7bpYHV7nhElkgQTPROvDQg=="
        },
        "likes_count": 5
      },
      {
        "id": 17853007241557121,
        "created_at": 1623683686,
        "text": "@7bpYHV7nhElkgQTPROvDQg== Ich habe es mehrfach versucht, aber spätestens 1944 wird es schwierig. Ich bin zu emotional",
        "owner": {
          "id": "W_cWctkaUGyE670CzFanJQ==",
          "username": "PhcL3suZ7R1Wri6_Ndqrug=="
        },
        "likes_count": 4
      }
    ]
  },
  {
    "id": 17949681574469263,
    "created_at": 1623657026,
    "text": "Weiter studieren wäre auf jeden Fall sinnvoll. Du kannst in der „Machthirarchie“ aufsteigen und so mehr bewirken.",
    "owner": {
      "id": "yZSTW-eiyIp8bdK0otUQLQ==",
      "username": "QYc02GRwr_Fjlv7K2EIkLw=="
    },
    "likes_count": 16,
    "answers": [
      {
        "id": 17877268667412585,
        "created_at": 1623679861,
        "text": "@mQXmGWwsZUPA4AdcmiagJg== Aber das würde doch Sophies Einstellungen zuwider laufen. Wir reden hier über eine Diktatur. In der Machthierarchie aufzusteigen ist gleichbedeutend mit, sich der NS-Ideologie fügen. Und was sich am Ende ändert, entschied  immer noch der Führer.",
        "owner": {
          "id": "7MwbIOHXcqEF3zGGp_S0hA==",
          "username": "EDXUd4fq1-uAN0Tooi9m_Q=="
        },
        "likes_count": 1
      }
    ]
  },
  {
    "id": 17900902886018332,
    "created_at": 1623656338,
    "text": "Ich kann mir nicht vorstellen, wie es war in dieser Zeit zu studieren…aber mit heutigem Wissen diese widerwärtigen Gesetze studieren zu müssen wäre 🤢 gewesen. Auf der anderen Seite konnte man zu dem Zeitpunkt ja nicht wissen, wie es mit diesem Regime weiterging. Also musste man ja wenigstens etwas machen um eine Lebensgrundlage zu haben. Mit heutigem Wissen würde man es sicher anders machen aber damals hätte ich sicher auch weiterstudiert. Schon krass in welche Lage junge Leute gebracht wurden..heute setzen sich ja auch viele studis nicht mit ihrem politischen System und der Geschichte auseinander und ziehen ihr Studium durch ohne nach links u rechts zu schauen - sehr schade",
    "owner": {
      "id": "mhid_GB4n3JMSlT9HYAKDA==",
      "username": "VXHlyGY2lOUeQHlVmLjBpg=="
    },
    "likes_count": 29,
    "answers": []
  },
  {
    "id": 18135318250174831,
    "created_at": 1623656099,
    "text": "Man muss die Fehler kennen um es besser machen zu können",
    "owner": {
      "id": "1UdW4bbfqLORwC17fQhnrQ==",
      "username": "_cv8MKeTGRY3uM7Llt-tHw=="
    },
    "likes_count": 20,
    "answers": []
  },
  {
    "id": 17906488696928767,
    "created_at": 1623655991,
    "text": "Der Widerstand gegen die Nazis ist Vorbild für alle Generationen!",
    "owner": {
      "id": "gjlTlestg0IlQl2J4erRBA==",
      "username": "K_KlUxXOptd1ZDmmhpJLmQ=="
    },
    "likes_count": 61,
    "answers": []
  },
  {
    "id": 18117574219238738,
    "created_at": 1623655864,
    "text": "🙌🙌",
    "owner": {
      "id": "-UyADcp6o0S48Est8ddMnw==",
      "username": "mwA3EuKaQxewxH7f0RbOYw=="
    },
    "likes_count": 5,
    "answers": []
  }
]