[
  {
    "id": 18042681001311498,
    "created_at": 1641967012,
    
    "owner": {
      "id": "MbGJyJUuLIiaqgFq2DKTkA==",
      "username": "5K2VAyLZ2LZ4YdQ_bEgscA=="
    },
    "likes_count": 0,
    "answers": []
  },
  {
    "id": 17915825360100124,
    "created_at": 1641557550,
    
    "owner": {
      "id": "LY5WKrmdK7q4T4d1sUgc6g==",
      "username": "k3r4LcktaMACrAUy8M5L6A=="
    },
    "likes_count": 0,
    "answers": []
  },
  {
    "id": 18146723638234889,
    "created_at": 1640812727,
    
    "owner": {
      "id": "UnBo_ynic_xPkoMGFFUS-Q==",
      "username": "VQ-9cP5nTKV34ANiT_UHOQ=="
    },
    "likes_count": 0,
    "answers": [
      {
        "id": 17907518729484096,
        "created_at": 1640853893,
        
        "owner": {
          "id": "9rICyTfoSV8xPafAZ0Xo0w==",
          "username": "hib4mKmHA-vgwtwb0Q_04A=="
        },
        "likes_count": 0
      }
    ]
  },
  {
    "id": 17913166043114194,
    "created_at": 1640789391,
    
    "owner": {
      "id": "IK7C5VkyKYXdqbHDgPZjdw==",
      "username": "dRMAqJxiVKF9Uhslm-FTsw=="
    },
    "likes_count": 0,
    "answers": [
      {
        "id": 18214125946106158,
        "created_at": 1640790169,
        
        "owner": {
          "id": "9rICyTfoSV8xPafAZ0Xo0w==",
          "username": "hib4mKmHA-vgwtwb0Q_04A=="
        },
        "likes_count": 1
      }
    ]
  },
  {
    "id": 17858357522641669,
    "created_at": 1640721127,
    
    "owner": {
      "id": "-yeTrCbqZwG_03ht6eDNQQ==",
      "username": "kigXulXquSBs16_DkZ6C-A=="
    },
    "likes_count": 0,
    "answers": [
      {
        "id": 17903808185299317,
        "created_at": 1640771602,
        
        "owner": {
          "id": "9rICyTfoSV8xPafAZ0Xo0w==",
          "username": "hib4mKmHA-vgwtwb0Q_04A=="
        },
        "likes_count": 2
      }
    ]
  },
  {
    "id": 17933113231798026,
    "created_at": 1640715137,
    
    "owner": {
      "id": "tHhsBln1Eg07izmyBHwkfg==",
      "username": "nDED6rWXM5XQlTK5S5OFXw=="
    },
    "likes_count": 3,
    "answers": [
      {
        "id": 18256560409076121,
        "created_at": 1640716947,
        
        "owner": {
          "id": "BgHwq7d7GwT4br6aRwD6iA==",
          "username": "J73HYFZEN1cUbwDvddKTIQ=="
        },
        "likes_count": 5
      },
      {
        "id": 18182257510084452,
        "created_at": 1640864114,
        
        "owner": {
          "id": "Oo3nZqgi0iN0vtRcTBG4vw==",
          "username": "5EIQtIf4HC1d0zRBxjB3jw=="
        },
        "likes_count": 5
      },
      {
        "id": 18120355252251877,
        "created_at": 1640778394,
        
        "owner": {
          "id": "tHhsBln1Eg07izmyBHwkfg==",
          "username": "nDED6rWXM5XQlTK5S5OFXw=="
        },
        "likes_count": 2
      },
      {
        "id": 18118273273258052,
        "created_at": 1640821331,
        
        "owner": {
          "id": "tHhsBln1Eg07izmyBHwkfg==",
          "username": "nDED6rWXM5XQlTK5S5OFXw=="
        },
        "likes_count": 2
      },
      {
        "id": 18104487646284722,
        "created_at": 1640777815,
        
        "owner": {
          "id": "tHhsBln1Eg07izmyBHwkfg==",
          "username": "nDED6rWXM5XQlTK5S5OFXw=="
        },
        "likes_count": 2
      },
      {
        "id": 18074962390291908,
        "created_at": 1640792590,
        
        "owner": {
          "id": "tHhsBln1Eg07izmyBHwkfg==",
          "username": "nDED6rWXM5XQlTK5S5OFXw=="
        },
        "likes_count": 0
      },
      {
        "id": 18000154261370572,
        "created_at": 1640862712,
        
        "owner": {
          "id": "BgHwq7d7GwT4br6aRwD6iA==",
          "username": "J73HYFZEN1cUbwDvddKTIQ=="
        },
        "likes_count": 1
      },
      {
        "id": 17993275411409229,
        "created_at": 1640862082,
        
        "owner": {
          "id": "tHhsBln1Eg07izmyBHwkfg==",
          "username": "nDED6rWXM5XQlTK5S5OFXw=="
        },
        "likes_count": 0
      },
      {
        "id": 17993052487407660,
        "created_at": 1640798213,
        
        "owner": {
          "id": "BgHwq7d7GwT4br6aRwD6iA==",
          "username": "J73HYFZEN1cUbwDvddKTIQ=="
        },
        "likes_count": 1
      },
      {
        "id": 17929789624844028,
        "created_at": 1640863390,
        
        "owner": {
          "id": "fSgdKhU7AfEcscu92LytWA==",
          "username": "Guu8kXCHRq9lEWSnV9KsrA=="
        },
        "likes_count": 3
      },
      {
        "id": 17925596465056828,
        "created_at": 1640793731,
        
        "owner": {
          "id": "fSgdKhU7AfEcscu92LytWA==",
          "username": "Guu8kXCHRq9lEWSnV9KsrA=="
        },
        "likes_count": 2
      },
      {
        "id": 17920537586002277,
        "created_at": 1640863506,
        
        "owner": {
          "id": "BgHwq7d7GwT4br6aRwD6iA==",
          "username": "J73HYFZEN1cUbwDvddKTIQ=="
        },
        "likes_count": 3
      },
      {
        "id": 17911516865152891,
        "created_at": 1640779796,
        
        "owner": {
          "id": "BgHwq7d7GwT4br6aRwD6iA==",
          "username": "J73HYFZEN1cUbwDvddKTIQ=="
        },
        "likes_count": 2
      },
      {
        "id": 17891064089482711,
        "created_at": 1640861355,
        
        "owner": {
          "id": "9rICyTfoSV8xPafAZ0Xo0w==",
          "username": "hib4mKmHA-vgwtwb0Q_04A=="
        },
        "likes_count": 0
      },
      {
        "id": 17886572150551847,
        "created_at": 1640715201,
        
        "owner": {
          "id": "tHhsBln1Eg07izmyBHwkfg==",
          "username": "nDED6rWXM5XQlTK5S5OFXw=="
        },
        "likes_count": 4
      },
      {
        "id": 17878639904611144,
        "created_at": 1640792917,
        
        "owner": {
          "id": "tHhsBln1Eg07izmyBHwkfg==",
          "username": "nDED6rWXM5XQlTK5S5OFXw=="
        },
        "likes_count": 0
      },
      {
        "id": 17869698335598143,
        "created_at": 1640790011,
        
        "owner": {
          "id": "9rICyTfoSV8xPafAZ0Xo0w==",
          "username": "hib4mKmHA-vgwtwb0Q_04A=="
        },
        "likes_count": 0
      },
      {
        "id": 17864398856632603,
        "created_at": 1640777606,
        
        "owner": {
          "id": "9rICyTfoSV8xPafAZ0Xo0w==",
          "username": "hib4mKmHA-vgwtwb0Q_04A=="
        },
        "likes_count": 0
      }
    ]
  },
  {
    "id": 17939639476748674,
    "created_at": 1640714977,
    
    "owner": {
      "id": "ckotqO3tyqwpGEScBXtH9A==",
      "username": "oKeETlAgxKC5p_WM_1IBIw=="
    },
    "likes_count": 0,
    "answers": [
      {
        "id": 17898273998518397,
        "created_at": 1641376628,
        
        "owner": {
          "id": "0U6sakbVBEn2OgvWF0ADsA==",
          "username": "gdsvW44_Sbp_jZeuU6sJ3Q=="
        },
        "likes_count": 0
      }
    ]
  },
  {
    "id": 18275360497006926,
    "created_at": 1640712352,
    
    "owner": {
      "id": "MJUHcq3d7NeGt7bOyDI9WA==",
      "username": "_3jh0wrg1egfG9E6qu7Fqg=="
    },
    "likes_count": 0,
    "answers": [
      {
        "id": 17908594481204520,
        "created_at": 1641137498,
        
        "owner": {
          "id": "0U6sakbVBEn2OgvWF0ADsA==",
          "username": "gdsvW44_Sbp_jZeuU6sJ3Q=="
        },
        "likes_count": 0
      }
    ]
  },
  {
    "id": 17895520754395510,
    "created_at": 1640711395,
    
    "owner": {
      "id": "iO1g1jBZdZULGNPpswSj2A==",
      "username": "lR8YX6G1P2I4opBHPMdGXg=="
    },
    "likes_count": 1,
    "answers": [
      {
        "id": 18020570707350422,
        "created_at": 1640725576,
        
        "owner": {
          "id": "0U6sakbVBEn2OgvWF0ADsA==",
          "username": "gdsvW44_Sbp_jZeuU6sJ3Q=="
        },
        "likes_count": 0
      }
    ]
  },
  {
    "id": 18140551717217529,
    "created_at": 1640707034,
    
    "owner": {
      "id": "x2oK2iJpHzGK436NnpXw9A==",
      "username": "VSj_lqtGpFwgKV_SPYVQSg=="
    },
    "likes_count": 0,
    "answers": [
      {
        "id": 17968488700499191,
        "created_at": 1640717801,
        
        "owner": {
          "id": "Sznqs_dP9U6h4arGo54ubQ==",
          "username": "oOI4h7dIKKd_moaKpzieag=="
        },
        "likes_count": 1
      }
    ]
  },
  {
    "id": 17950981990564553,
    "created_at": 1640703292,
    
    "owner": {
      "id": "IS3eRit1vWdt3At5winmQQ==",
      "username": "a4S-D-8ElUnn9QDoTE6bYg=="
    },
    "likes_count": 1,
    "answers": []
  },
  {
    "id": 17902167014389211,
    "created_at": 1640701003,
    
    "owner": {
      "id": "Cq7FJpbjZi9tX7U9aY5C7w==",
      "username": "0bKnMX0YwYSwfPPng9DrcQ=="
    },
    "likes_count": 5,
    "answers": [
      {
        "id": 17913522884207899,
        "created_at": 1640723986,
        
        "owner": {
          "id": "Zc0o7s-XGdcrhkCb77n-vA==",
          "username": "Apv507XL_j7V4_QOa8RdKw=="
        },
        "likes_count": 1
      }
    ]
  },
  {
    "id": 17920087169109334,
    "created_at": 1640700558,
    
    "owner": {
      "id": "YXqTqSaUw2_xZhXwebpYjg==",
      "username": "aHc2rRun1OC9GF-hmbnQVQ=="
    },
    "likes_count": 17,
    "answers": []
  },
  {
    "id": 17932713004807247,
    "created_at": 1640695419,
    
    "owner": {
      "id": "xPhT6gxKio2Pw38rWA5Mgg==",
      "username": "z3bAneFC8x9k3J00fAxBqQ=="
    },
    "likes_count": 3,
    "answers": []
  },
  {
    "id": 17922022600975161,
    "created_at": 1640695043,
    
    "owner": {
      "id": "2Ap0iAAmf9Fl8TfcJXYckQ==",
      "username": "ZRBeckj1buEaQlZ2zubAoA=="
    },
    "likes_count": 2,
    "answers": []
  },
  {
    "id": 18215955193129907,
    "created_at": 1640695040,
    
    "owner": {
      "id": "0U6sakbVBEn2OgvWF0ADsA==",
      "username": "gdsvW44_Sbp_jZeuU6sJ3Q=="
    },
    "likes_count": 2,
    "answers": []
  },
  {
    "id": 17934523414751774,
    "created_at": 1640693435,
    
    "owner": {
      "id": "mQ-xGodjm6ipiI9YamgARQ==",
      "username": "pSXsIny-92-ysecof_apaQ=="
    },
    "likes_count": 3,
    "answers": []
  },
  {
    "id": 18263722309065840,
    "created_at": 1640692133,
    
    "owner": {
      "id": "_xIr4INGqUd-8kO8NJ565w==",
      "username": "hUBZsQDxL_6DjJ22N7nElw=="
    },
    "likes_count": 2,
    "answers": []
  },
  {
    "id": 17918221361139484,
    "created_at": 1640692102,
    
    "owner": {
      "id": "n0ml_GL7_0klVwqPnVDTHA==",
      "username": "v0SarFRRsiOK0iGrx1IODA=="
    },
    "likes_count": 4,
    "answers": [
      {
        "id": 18001601194390895,
        "created_at": 1640935492,
        
        "owner": {
          "id": "n0ml_GL7_0klVwqPnVDTHA==",
          "username": "v0SarFRRsiOK0iGrx1IODA=="
        },
        "likes_count": 0
      },
      {
        "id": 17947000387637344,
        "created_at": 1640714911,
        
        "owner": {
          "id": "tHhsBln1Eg07izmyBHwkfg==",
          "username": "nDED6rWXM5XQlTK5S5OFXw=="
        },
        "likes_count": 1
      },
      {
        "id": 17914190780106726,
        "created_at": 1640703216,
        
        "owner": {
          "id": "n0ml_GL7_0klVwqPnVDTHA==",
          "username": "v0SarFRRsiOK0iGrx1IODA=="
        },
        "likes_count": 0
      },
      {
        "id": 17911710608261296,
        "created_at": 1640697916,
        
        "owner": {
          "id": "eTvPN2BRgnRCoWy6J0kScg==",
          "username": "UaxO5w_VoUOEoiXQzynjBQ=="
        },
        "likes_count": 0
      },
      {
        "id": 17899244111513572,
        "created_at": 1640692901,
        
        "owner": {
          "id": "tHhsBln1Eg07izmyBHwkfg==",
          "username": "nDED6rWXM5XQlTK5S5OFXw=="
        },
        "likes_count": 0
      },
      {
        "id": 17897425517346830,
        "created_at": 1640692730,
        
        "owner": {
          "id": "zUEvsDlZU-Y8uiOL9CKIzA==",
          "username": "r_Spv_2HGP5cuX38s1TLKA=="
        },
        "likes_count": 8
      }
    ]
  },
  {
    "id": 18141128197217470,
    "created_at": 1640691587,
    
    "owner": {
      "id": "tHhsBln1Eg07izmyBHwkfg==",
      "username": "nDED6rWXM5XQlTK5S5OFXw=="
    },
    "likes_count": 7,
    "answers": []
  },
  {
    "id": 18141738466242332,
    "created_at": 1640690499,
    
    "owner": {
      "id": "RbXpwofpfehoSTSz4ArNUw==",
      "username": "Wa9fbPWf2z3-VQOi40J-vw=="
    },
    "likes_count": 4,
    "answers": []
  },
  {
    "id": 18212641588187284,
    "created_at": 1640690016,
    
    "owner": {
      "id": "jjWilhkH6zNrRkjCuZOALA==",
      "username": "lJJYAyb2enujmcspiE4zug=="
    },
    "likes_count": 2,
    "answers": [
      {
        "id": 18001029664391656,
        "created_at": 1640693809,
        
        "owner": {
          "id": "gVIApis6_hcUwwGsshrdOQ==",
          "username": "VdIPP100WgUDyN3onJdGRw=="
        },
        "likes_count": 2
      }
    ]
  },
  {
    "id": 17941938115699241,
    "created_at": 1640688696,
    
    "owner": {
      "id": "-A5zBPinHcjI0zw163JGNg==",
      "username": "WllVzs6P5DtVppsIahUbeQ=="
    },
    "likes_count": 4,
    "answers": [
      {
        "id": 18034449346318281,
        "created_at": 1640690207,
        
        "owner": {
          "id": "tHhsBln1Eg07izmyBHwkfg==",
          "username": "nDED6rWXM5XQlTK5S5OFXw=="
        },
        "likes_count": 9
      },
      {
        "id": 17954381122535150,
        "created_at": 1640693086,
        
        "owner": {
          "id": "9rICyTfoSV8xPafAZ0Xo0w==",
          "username": "hib4mKmHA-vgwtwb0Q_04A=="
        },
        "likes_count": 17
      },
      {
        "id": 17950034245626811,
        "created_at": 1640701106,
        
        "owner": {
          "id": "cYXkbqY3EhlB90MqkMHrqA==",
          "username": "ZbL1ZTwuujzY-1iQ_HSbrw=="
        },
        "likes_count": 2
      },
      {
        "id": 17914651445192167,
        "created_at": 1640689864,
        
        "owner": {
          "id": "WCvKFQOJZ9Nps46QU5naiw==",
          "username": "Fy-DLa3DTwl8nhY6R4Sr0A=="
        },
        "likes_count": 9
      }
    ]
  },
  {
    "id": 17924949707012960,
    "created_at": 1640688659,
    
    "owner": {
      "id": "8B0oFLagY2UOq5J6XD0l0g==",
      "username": "6LVSbEWWgyFB69pkfREKDg=="
    },
    "likes_count": 0,
    "answers": [
      {
        "id": 18027782989332698,
        "created_at": 1640693426,
        
        "owner": {
          "id": "9rICyTfoSV8xPafAZ0Xo0w==",
          "username": "hib4mKmHA-vgwtwb0Q_04A=="
        },
        "likes_count": 7
      },
      {
        "id": 17910313988164826,
        "created_at": 1640694773,
        
        "owner": {
          "id": "WCvKFQOJZ9Nps46QU5naiw==",
          "username": "Fy-DLa3DTwl8nhY6R4Sr0A=="
        },
        "likes_count": 3
      }
    ]
  },
  {
    "id": 18273497080036421,
    "created_at": 1640688585,
    
    "owner": {
      "id": "8B0oFLagY2UOq5J6XD0l0g==",
      "username": "6LVSbEWWgyFB69pkfREKDg=="
    },
    "likes_count": 14,
    "answers": [
      {
        "id": 17861617610631839,
        "created_at": 1640692858,
        
        "owner": {
          "id": "9rICyTfoSV8xPafAZ0Xo0w==",
          "username": "hib4mKmHA-vgwtwb0Q_04A=="
        },
        "likes_count": 11
      }
    ]
  },
  {
    "id": 17977536997459575,
    "created_at": 1640688560,
    
    "owner": {
      "id": "8B0oFLagY2UOq5J6XD0l0g==",
      "username": "6LVSbEWWgyFB69pkfREKDg=="
    },
    "likes_count": 0,
    "answers": [
      {
        "id": 17947652233630314,
        "created_at": 1640699040,
        
        "owner": {
          "id": "WCvKFQOJZ9Nps46QU5naiw==",
          "username": "Fy-DLa3DTwl8nhY6R4Sr0A=="
        },
        "likes_count": 0
      },
      {
        "id": 17927630131985857,
        "created_at": 1640694911,
        
        "owner": {
          "id": "9rICyTfoSV8xPafAZ0Xo0w==",
          "username": "hib4mKmHA-vgwtwb0Q_04A=="
        },
        "likes_count": 2
      },
      {
        "id": 17894916539419068,
        "created_at": 1640697415,
        
        "owner": {
          "id": "WCvKFQOJZ9Nps46QU5naiw==",
          "username": "Fy-DLa3DTwl8nhY6R4Sr0A=="
        },
        "likes_count": 1
      },
      {
        "id": 17847703247688272,
        "created_at": 1640698844,
        
        "owner": {
          "id": "9rICyTfoSV8xPafAZ0Xo0w==",
          "username": "hib4mKmHA-vgwtwb0Q_04A=="
        },
        "likes_count": 12
      }
    ]
  },
  {
    "id": 17910196460170929,
    "created_at": 1640688341,
    
    "owner": {
      "id": "0JGy1vW9l58a9uf5oEdpLw==",
      "username": "kaLhFxgcO_vBDDvxpYIEDw=="
    },
    "likes_count": 3,
    "answers": [
      {
        "id": 18273169375059671,
        "created_at": 1640692821,
        
        "owner": {
          "id": "9rICyTfoSV8xPafAZ0Xo0w==",
          "username": "hib4mKmHA-vgwtwb0Q_04A=="
        },
        "likes_count": 6
      }
    ]
  },
  {
    "id": 17885790680582380,
    "created_at": 1640688167,
    
    "owner": {
      "id": "Y3p79Bw7ECVtiiZsIFPwfw==",
      "username": "Yp_V4346cxD83Hk9DDP2Dg=="
    },
    "likes_count": 2,
    "answers": []
  },
  {
    "id": 17914574558231113,
    "created_at": 1640687414,
    
    "owner": {
      "id": "wkGqOfC72KqJohz8w5FJpg==",
      "username": "YYfnwoOH7-wowBkV9pl6hA=="
    },
    "likes_count": 9,
    "answers": [
      {
        "id": 18158355805205702,
        "created_at": 1640805565,
        
        "owner": {
          "id": "0U6sakbVBEn2OgvWF0ADsA==",
          "username": "gdsvW44_Sbp_jZeuU6sJ3Q=="
        },
        "likes_count": 1
      },
      {
        "id": 18148259512228104,
        "created_at": 1640695590,
        
        "owner": {
          "id": "0U6sakbVBEn2OgvWF0ADsA==",
          "username": "gdsvW44_Sbp_jZeuU6sJ3Q=="
        },
        "likes_count": 4
      },
      {
        "id": 18000535315384744,
        "created_at": 1640692199,
        
        "owner": {
          "id": "9rICyTfoSV8xPafAZ0Xo0w==",
          "username": "hib4mKmHA-vgwtwb0Q_04A=="
        },
        "likes_count": 4
      },
      {
        "id": 17933733211783025,
        "created_at": 1640695734,
        
        "owner": {
          "id": "0U6sakbVBEn2OgvWF0ADsA==",
          "username": "gdsvW44_Sbp_jZeuU6sJ3Q=="
        },
        "likes_count": 2
      },
      {
        "id": 17854518530679796,
        "created_at": 1640804026,
        
        "owner": {
          "id": "wkGqOfC72KqJohz8w5FJpg==",
          "username": "YYfnwoOH7-wowBkV9pl6hA=="
        },
        "likes_count": 1
      }
    ]
  },
  {
    "id": 18159028249170603,
    "created_at": 1640687027,
    
    "owner": {
      "id": "tHhsBln1Eg07izmyBHwkfg==",
      "username": "nDED6rWXM5XQlTK5S5OFXw=="
    },
    "likes_count": 13,
    "answers": []
  },
  {
    "id": 18270933607002642,
    "created_at": 1640686440,
    
    "owner": {
      "id": "B3B5uu6rHvTmwMBeBXVGkQ==",
      "username": "vNw347RiqQBAKaoGB5wnVA=="
    },
    "likes_count": 2,
    "answers": [
      {
        "id": 17987054878425077,
        "created_at": 1640687810,
        
        "owner": {
          "id": "WCvKFQOJZ9Nps46QU5naiw==",
          "username": "Fy-DLa3DTwl8nhY6R4Sr0A=="
        },
        "likes_count": 2
      },
      {
        "id": 17926855309993372,
        "created_at": 1640688484,
        
        "owner": {
          "id": "E7XOnIMmYcI6PS2ijcxC_A==",
          "username": "ZwhQtKzWuQbLrgDvSJkSSw=="
        },
        "likes_count": 0
      },
      {
        "id": 17911328147147552,
        "created_at": 1640688511,
        
        "owner": {
          "id": "Vlzkypqpat1d94x-7J_QyQ==",
          "username": "GFuGBLFGyLvLfMXDm9Xa-A=="
        },
        "likes_count": 2
      }
    ]
  },
  {
    "id": 18199012759123087,
    "created_at": 1640686198,
    
    "owner": {
      "id": "WCvKFQOJZ9Nps46QU5naiw==",
      "username": "Fy-DLa3DTwl8nhY6R4Sr0A=="
    },
    "likes_count": 28,
    "answers": []
  },
  {
    "id": 17912697728204366,
    "created_at": 1640686117,
    
    "owner": {
      "id": "2wtNnlwgZuDliA3nz-cHHw==",
      "username": "g0h7RXrC__8pvJBjrgNUDA=="
    },
    "likes_count": 0,
    "answers": []
  },
  {
    "id": 17970023308489890,
    "created_at": 1640686074,
    
    "owner": {
      "id": "TVA-ZrHCmrv1LUBeSdjssw==",
      "username": "Za0sekGoomA_Wnck5sF5xg=="
    },
    "likes_count": 4,
    "answers": [
      {
        "id": 17906969771219950,
        "created_at": 1640686172,
        
        "owner": {
          "id": "tHhsBln1Eg07izmyBHwkfg==",
          "username": "nDED6rWXM5XQlTK5S5OFXw=="
        },
        "likes_count": 17
      }
    ]
  },
  {
    "id": 17933765209777259,
    "created_at": 1640686056,
    
    "owner": {
      "id": "GGoKChEjiainSdUaDUjKxw==",
      "username": "IWMM6HMvUzwF3B4jwwMAYQ=="
    },
    "likes_count": 5,
    "answers": []
  },
  {
    "id": 17852168285665106,
    "created_at": 1640685901,
    
    "owner": {
      "id": "-u_xa6FDZXsKHGmt9hP0yw==",
      "username": "obcUeHzKMQjLU183_nGE7Q=="
    },
    "likes_count": 4,
    "answers": [
      {
        "id": 18286881691063067,
        "created_at": 1640735194,
        
        "owner": {
          "id": "7hUL0AlifGmWUSux-Sj0bQ==",
          "username": "OWManVSqgChIoLMdvYBSCA=="
        },
        "likes_count": 3
      },
      {
        "id": 17942732698697808,
        "created_at": 1640691421,
        
        "owner": {
          "id": "BgHwq7d7GwT4br6aRwD6iA==",
          "username": "J73HYFZEN1cUbwDvddKTIQ=="
        },
        "likes_count": 9
      },
      {
        "id": 17926206754988587,
        "created_at": 1640689629,
        
        "owner": {
          "id": "DMHF9LLoRxRy1EYkv3xRrg==",
          "username": "WSMggsdlZ5CxsPVI9jo1wA=="
        },
        "likes_count": 1
      },
      {
        "id": 17924616937914540,
        "created_at": 1640778121,
        
        "owner": {
          "id": "BgHwq7d7GwT4br6aRwD6iA==",
          "username": "J73HYFZEN1cUbwDvddKTIQ=="
        },
        "likes_count": 0
      },
      {
        "id": 17884699997590553,
        "created_at": 1640725340,
        
        "owner": {
          "id": "0U6sakbVBEn2OgvWF0ADsA==",
          "username": "gdsvW44_Sbp_jZeuU6sJ3Q=="
        },
        "likes_count": 1
      }
    ]
  },
  {
    "id": 17954218873585921,
    "created_at": 1640685761,
    
    "owner": {
      "id": "tHhsBln1Eg07izmyBHwkfg==",
      "username": "nDED6rWXM5XQlTK5S5OFXw=="
    },
    "likes_count": 17,
    "answers": []
  },
  {
    "id": 17848325678694418,
    "created_at": 1640685652,
    
    "owner": {
      "id": "9rICyTfoSV8xPafAZ0Xo0w==",
      "username": "hib4mKmHA-vgwtwb0Q_04A=="
    },
    "likes_count": 280,
    "answers": [
      {
        "id": 17925616517015051,
        "created_at": 1640689580,
        
        "owner": {
          "id": "BgHwq7d7GwT4br6aRwD6iA==",
          "username": "J73HYFZEN1cUbwDvddKTIQ=="
        },
        "likes_count": 21
      },
      {
        "id": 17910936080334069,
        "created_at": 1640721580,
        
        "owner": {
          "id": "Rc_EfXSMN-j0WUrwtiaf6w==",
          "username": "DqMgIuddo7p8rFDHsAe-Ew=="
        },
        "likes_count": 2
      }
    ]
  }
]