[
  {
    "id": 18169012198088900,
    "created_at": 1632040770,
    
    "owner": {
      "id": "ssKw_3Qtw1rtxOf7gp_f2w==",
      "username": "_KNC_C-T5n4Skqa47ZIPBA=="
    },
    "likes_count": 0,
    "answers": []
  },
  {
    "id": 17908844459007104,
    "created_at": 1631878818,
    
    "owner": {
      "id": "wZ_lE-o8g9BjXdJ4W3Hdog==",
      "username": "knPfQTc1GMCKe4oSOZB7YQ=="
    },
    "likes_count": 2,
    "answers": [
      {
        "id": 18133357411231807,
        "created_at": 1631879758,
        
        "owner": {
          "id": "9rICyTfoSV8xPafAZ0Xo0w==",
          "username": "hib4mKmHA-vgwtwb0Q_04A=="
        },
        "likes_count": 1
      }
    ]
  },
  {
    "id": 17953168276503104,
    "created_at": 1631854683,
    
    "owner": {
      "id": "wZ_lE-o8g9BjXdJ4W3Hdog==",
      "username": "knPfQTc1GMCKe4oSOZB7YQ=="
    },
    "likes_count": 0,
    "answers": [
      {
        "id": 17927980477757677,
        "created_at": 1631864272,
        
        "owner": {
          "id": "9rICyTfoSV8xPafAZ0Xo0w==",
          "username": "hib4mKmHA-vgwtwb0Q_04A=="
        },
        "likes_count": 0
      }
    ]
  },
  {
    "id": 17979854932376387,
    "created_at": 1631813951,
    
    "owner": {
      "id": "jV-4uFzqgR40tH4HWkt76g==",
      "username": "85pfvnWN64fNL1q9VJu6ug=="
    },
    "likes_count": 0,
    "answers": []
  },
  {
    "id": 17877292874525882,
    "created_at": 1631784561,
    
    "owner": {
      "id": "deCv9LwwcZBt4daH5Hb1Vg==",
      "username": "0yYO1UW9bS0Y6-f_u1AnsA=="
    },
    "likes_count": 0,
    "answers": [
      {
        "id": 17892470192495373,
        "created_at": 1631786546,
        
        "owner": {
          "id": "9rICyTfoSV8xPafAZ0Xo0w==",
          "username": "hib4mKmHA-vgwtwb0Q_04A=="
        },
        "likes_count": 1
      }
    ]
  },
  {
    "id": 17919872167816295,
    "created_at": 1631768945,
    
    "owner": {
      "id": "c1YsfJZHOJdKme-dHZlZlg==",
      "username": "YSyVm8I_eAHxQCfGtaJOaw=="
    },
    "likes_count": 0,
    "answers": [
      {
        "id": 18194207497115572,
        "created_at": 1631786117,
        
        "owner": {
          "id": "9rICyTfoSV8xPafAZ0Xo0w==",
          "username": "hib4mKmHA-vgwtwb0Q_04A=="
        },
        "likes_count": 1
      }
    ]
  },
  {
    "id": 17997606409370276,
    "created_at": 1631766017,
    
    "owner": {
      "id": "BzilUkWgT-h_gTeKtUGtgg==",
      "username": "RpI8nSi7M8Hzy6xjvGl5iQ=="
    },
    "likes_count": 0,
    "answers": [
      {
        "id": 17885132252374797,
        "created_at": 1631788748,
        
        "owner": {
          "id": "xnKE9QCC8KDktVW3-rTNgg==",
          "username": "ykhsRuXNQmuWUqCsJI_NBA=="
        },
        "likes_count": 0
      }
    ]
  },
  {
    "id": 18251232406013777,
    "created_at": 1631739451,
    
    "owner": {
      "id": "OfZI6M5WsOPg9nKlGU5PVg==",
      "username": "tmWE9oWV3wykCOzrf4N0Ww=="
    },
    "likes_count": 1,
    "answers": [
      {
        "id": 18147309499175961,
        "created_at": 1631786646,
        
        "owner": {
          "id": "9rICyTfoSV8xPafAZ0Xo0w==",
          "username": "hib4mKmHA-vgwtwb0Q_04A=="
        },
        "likes_count": 1
      }
    ]
  },
  {
    "id": 18169538917094092,
    "created_at": 1631738912,
    
    "owner": {
      "id": "lKaybW1n3IMVW3yXtpcsPA==",
      "username": "49cg-TiK3XXG9dbsjbpxaA=="
    },
    "likes_count": 0,
    "answers": [
      {
        "id": 17957541358488127,
        "created_at": 1631796298,
        
        "owner": {
          "id": "lKaybW1n3IMVW3yXtpcsPA==",
          "username": "49cg-TiK3XXG9dbsjbpxaA=="
        },
        "likes_count": 1
      },
      {
        "id": 17904742826067977,
        "created_at": 1631785604,
        
        "owner": {
          "id": "9rICyTfoSV8xPafAZ0Xo0w==",
          "username": "hib4mKmHA-vgwtwb0Q_04A=="
        },
        "likes_count": 1
      }
    ]
  },
  {
    "id": 17915358469895365,
    "created_at": 1631737201,
    
    "owner": {
      "id": "1_bqmjEOxW9n3rJJb3RX6A==",
      "username": "9TbJG2CbPe9tra9GKsyHHw=="
    },
    "likes_count": 0,
    "answers": []
  },
  {
    "id": 17870615927578318,
    "created_at": 1631729949,
    
    "owner": {
      "id": "y_RLft30YABEf5A4zJIw0w==",
      "username": "rEugu1mF100mojINmvJz9w=="
    },
    "likes_count": 0,
    "answers": [
      {
        "id": 18125917603241882,
        "created_at": 1631785574,
        
        "owner": {
          "id": "9rICyTfoSV8xPafAZ0Xo0w==",
          "username": "hib4mKmHA-vgwtwb0Q_04A=="
        },
        "likes_count": 1
      }
    ]
  },
  {
    "id": 17906867942110578,
    "created_at": 1631722906,
    
    "owner": {
      "id": "Qekqs8FSBx-7eFOSem50yw==",
      "username": "B0q0_HHmZU7EEp-GeSPKwg=="
    },
    "likes_count": 0,
    "answers": [
      {
        "id": 17947804234529943,
        "created_at": 1631785534,
        
        "owner": {
          "id": "9rICyTfoSV8xPafAZ0Xo0w==",
          "username": "hib4mKmHA-vgwtwb0Q_04A=="
        },
        "likes_count": 1
      }
    ]
  },
  {
    "id": 18254016343003910,
    "created_at": 1631719057,
    
    "owner": {
      "id": "10NzvMLnjbhcGmhbVLLhXA==",
      "username": "83mLr_m-s48T9p1rlukZmg=="
    },
    "likes_count": 0,
    "answers": []
  },
  {
    "id": 17866388618599034,
    "created_at": 1631713095,
    
    "owner": {
      "id": "JgEWrBfIy9vRJbsrnVvv3w==",
      "username": "5jcxZVV0snEjYwEGlaCYKg=="
    },
    "likes_count": 0,
    "answers": [
      {
        "id": 18251968069008947,
        "created_at": 1631785497,
        
        "owner": {
          "id": "9rICyTfoSV8xPafAZ0Xo0w==",
          "username": "hib4mKmHA-vgwtwb0Q_04A=="
        },
        "likes_count": 0
      }
    ]
  },
  {
    "id": 17888217500454395,
    "created_at": 1631712023,
    
    "owner": {
      "id": "ItGMao8t8o2GWfzE-3Kv9w==",
      "username": "YZiVB5k0k4uqVyEX8Ra_GQ=="
    },
    "likes_count": 0,
    "answers": [
      {
        "id": 17972540107431937,
        "created_at": 1631785426,
        
        "owner": {
          "id": "9rICyTfoSV8xPafAZ0Xo0w==",
          "username": "hib4mKmHA-vgwtwb0Q_04A=="
        },
        "likes_count": 0
      }
    ]
  },
  {
    "id": 17900153384126044,
    "created_at": 1631708683,
    
    "owner": {
      "id": "7_N1dj6PsRLhqc-ZXAt9XA==",
      "username": "r0w4TsnJyMahI7IjFEaS1g=="
    },
    "likes_count": 0,
    "answers": []
  },
  {
    "id": 17891196842305351,
    "created_at": 1631703882,
    
    "owner": {
      "id": "2Qw6FY8UZ58bdSej_3b2ZQ==",
      "username": "qttRiOoqYLeuHgDm9JauGA=="
    },
    "likes_count": 0,
    "answers": []
  },
  {
    "id": 17915114614962392,
    "created_at": 1631703099,
    
    "owner": {
      "id": "diFmoN_MTSY5mUXWfDWY2w==",
      "username": "OTOwJ4k_ROmSMlLWrUvIww=="
    },
    "likes_count": 0,
    "answers": []
  },
  {
    "id": 17946958846510434,
    "created_at": 1631702960,
    
    "owner": {
      "id": "nqARNjdJAx0VxE_n6cjY1Q==",
      "username": "usX0xnx33nua6oYnFrrFaA=="
    },
    "likes_count": 0,
    "answers": []
  },
  {
    "id": 18086801968287409,
    "created_at": 1631700837,
    
    "owner": {
      "id": "e3L-4teI6BtgjpcXfEKm2Q==",
      "username": "_mPtbBDwIhsxse-ib5uAVQ=="
    },
    "likes_count": 0,
    "answers": []
  },
  {
    "id": 17888221979426826,
    "created_at": 1631700102,
    
    "owner": {
      "id": "UWrxuQkmZmit6XTekR8DdA==",
      "username": "f37YR0DBPZNnCjxPDMjAKQ=="
    },
    "likes_count": 2,
    "answers": []
  },
  {
    "id": 17913809797992591,
    "created_at": 1631699836,
    
    "owner": {
      "id": "oiV_d1Kmw5mnYRlkqOpNYQ==",
      "username": "CkLV8XpmJiIWhKVH7_qVfw=="
    },
    "likes_count": 3,
    "answers": []
  },
  {
    "id": 17872131161555336,
    "created_at": 1631695546,
    
    "owner": {
      "id": "A-eHqpu82Ds1KV76-592IA==",
      "username": "ZfTx5EU45NnB0AX5Eg0kvQ=="
    },
    "likes_count": 1,
    "answers": []
  },
  {
    "id": 17952344458512675,
    "created_at": 1631692670,
    
    "owner": {
      "id": "sH4qEV5BAKg_rnF-zbu-rg==",
      "username": "j4CkJg25YMYSXKfBOmOVEw=="
    },
    "likes_count": 1,
    "answers": []
  },
  {
    "id": 17910385693973021,
    "created_at": 1631692655,
    
    "owner": {
      "id": "2KVow6KLR7S6gOkSZMcNrw==",
      "username": "-6UP1prAqobuhBoBPfhbKA=="
    },
    "likes_count": 1,
    "answers": []
  },
  {
    "id": 18184133917121941,
    "created_at": 1631692213,
    
    "owner": {
      "id": "ilGIM8AmqdPhL8d__CKN0w==",
      "username": "PXxhlWUMigIX_6Hj-zCzzw=="
    },
    "likes_count": 1,
    "answers": []
  },
  {
    "id": 17889088016435950,
    "created_at": 1631691942,
    
    "owner": {
      "id": "4Ko8vbOLC9g6FCrEKGtRbw==",
      "username": "H7KmzuTymVSSnFVg4fW_Aw=="
    },
    "likes_count": 1,
    "answers": []
  },
  {
    "id": 17919953494822413,
    "created_at": 1631691297,
    
    "owner": {
      "id": "p36QKkiCmlvjuYiEdouxFA==",
      "username": "aIZE1u16ECK943-CQ_faDA=="
    },
    "likes_count": 1,
    "answers": []
  },
  {
    "id": 17933886406657756,
    "created_at": 1631690978,
    
    "owner": {
      "id": "RghFMk3IolGXHpCbuos63w==",
      "username": "9sscNLntCXDtKVMKN7pU8A=="
    },
    "likes_count": 2,
    "answers": []
  },
  {
    "id": 18007316482344896,
    "created_at": 1631690965,
    
    "owner": {
      "id": "j1O6XoDIoN15BZsCwuvzKg==",
      "username": "U-W3FIdMpSpKgou5ONKEYw=="
    },
    "likes_count": 1,
    "answers": []
  },
  {
    "id": 17891790248299692,
    "created_at": 1631690810,
    
    "owner": {
      "id": "Ox47XB9vkMnlzGyMFVd10g==",
      "username": "G7kAwqhHmbNdDkQeha4EZg=="
    },
    "likes_count": 1,
    "answers": []
  },
  {
    "id": 17922834994865069,
    "created_at": 1631690663,
    
    "owner": {
      "id": "pi0n4XXY0aaHyc4EVCUNHw==",
      "username": "6gKEkpuqAOsSUg03rifP7w=="
    },
    "likes_count": 1,
    "answers": []
  },
  {
    "id": 17911479683068208,
    "created_at": 1631690458,
    
    "owner": {
      "id": "QXRZluTOKg1e-O4VOtB1Aw==",
      "username": "XfG7HhLjx3lLAR_X2Tn1nA=="
    },
    "likes_count": 1,
    "answers": []
  },
  {
    "id": 17927069344762456,
    "created_at": 1631690071,
    
    "owner": {
      "id": "uaiGr8CZ-pg1Il8gv9skcw==",
      "username": "dYsO5HtfomRDiWTbgIcn7Q=="
    },
    "likes_count": 1,
    "answers": []
  },
  {
    "id": 18184215286127960,
    "created_at": 1631689709,
    
    "owner": {
      "id": "8d2gvFL7S2RqHANXkD8o2Q==",
      "username": "IaalJaODJWqEHXn4rZk4vw=="
    },
    "likes_count": 19,
    "answers": [
      {
        "id": 18126351571240239,
        "created_at": 1631691081,
        
        "owner": {
          "id": "9rICyTfoSV8xPafAZ0Xo0w==",
          "username": "hib4mKmHA-vgwtwb0Q_04A=="
        },
        "likes_count": 17
      }
    ]
  },
  {
    "id": 17907149357115265,
    "created_at": 1631689560,
    
    "owner": {
      "id": "EEZcGghNf5IBRV_lgr_kig==",
      "username": "SNYXLOW5kxosmTuNPkrylw=="
    },
    "likes_count": 2,
    "answers": []
  },
  {
    "id": 17927244976775148,
    "created_at": 1631689319,
    
    "owner": {
      "id": "sHzF87Awt9x-7zGHR6YMdg==",
      "username": "7AGdmQXPGlVYitQbomIm_Q=="
    },
    "likes_count": 11,
    "answers": [
      {
        "id": 18249031867008237,
        "created_at": 1631693926,
        
        "owner": {
          "id": "9rICyTfoSV8xPafAZ0Xo0w==",
          "username": "hib4mKmHA-vgwtwb0Q_04A=="
        },
        "likes_count": 22
      },
      {
        "id": 17931507751730575,
        "created_at": 1631694992,
        
        "owner": {
          "id": "sHzF87Awt9x-7zGHR6YMdg==",
          "username": "7AGdmQXPGlVYitQbomIm_Q=="
        },
        "likes_count": 3
      }
    ]
  },
  {
    "id": 18098449435263834,
    "created_at": 1631689261,
    
    "owner": {
      "id": "hL9caNa9ZgH6tqxAJIGx2A==",
      "username": "nIOpkbirVP7iPTyJpjwk9Q=="
    },
    "likes_count": 1,
    "answers": []
  },
  {
    "id": 17929050391738301,
    "created_at": 1631689140,
    
    "owner": {
      "id": "gp39jefi2bYp4qtmvpZOug==",
      "username": "1SVNCeksZyeDeL2JvbrMhg=="
    },
    "likes_count": 0,
    "answers": []
  },
  {
    "id": 17905821740137759,
    "created_at": 1631688913,
    
    "owner": {
      "id": "-gKiIZee7yFe6J6R5MlaiA==",
      "username": "YZ3HpLUP33aKbFJEKeIYkg=="
    },
    "likes_count": 1,
    "answers": []
  },
  {
    "id": 18086912932286002,
    "created_at": 1631688492,
    
    "owner": {
      "id": "PnEFylIaK0lf4CGJqmsB1g==",
      "username": "6JPm_k4ebLAXHfdRxG4twA=="
    },
    "likes_count": 3,
    "answers": []
  },
  {
    "id": 17974544869425035,
    "created_at": 1631688402,
    
    "owner": {
      "id": "8LzHnjFjLOS7I4BbCvhzNA==",
      "username": "sUeb9ZoMc1z9B55fKUFjog=="
    },
    "likes_count": 2,
    "answers": []
  },
  {
    "id": 17851816379620168,
    "created_at": 1631688311,
    
    "owner": {
      "id": "BIAlUJ7ctsKi78mRjuYiGg==",
      "username": "0Pa__rAkArG_B-CNhMi6jQ=="
    },
    "likes_count": 1,
    "answers": []
  },
  {
    "id": 17888680595426564,
    "created_at": 1631688082,
    
    "owner": {
      "id": "D-_kWlkd_A2b0NfeS2sUnQ==",
      "username": "IplY4UhVrvG-J3HaU51uRA=="
    },
    "likes_count": 4,
    "answers": []
  },
  {
    "id": 17885597996359261,
    "created_at": 1631688050,
    
    "owner": {
      "id": "ESZ3THXUsbVbk82o_G5J7A==",
      "username": "U6rRsiqPNp2S2_DLDk7nEw=="
    },
    "likes_count": 2,
    "answers": []
  },
  {
    "id": 17922782818858519,
    "created_at": 1631687718,
    
    "owner": {
      "id": "80sphCfdTIk1kVJG_31rYA==",
      "username": "FRN7eSY2xWDb6n2ihfUBiQ=="
    },
    "likes_count": 3,
    "answers": []
  },
  {
    "id": 17903126558301327,
    "created_at": 1631687553,
    
    "owner": {
      "id": "lqaHGaEZytGMrYgL_cKA4g==",
      "username": "h9btCkp9m2_WeGUWfLl-Rw=="
    },
    "likes_count": 1,
    "answers": []
  },
  {
    "id": 17900262710205269,
    "created_at": 1631687303,
    
    "owner": {
      "id": "SIc7mP7TPYDIJOBlB0Ap2w==",
      "username": "0wDqYd1ew0rTt4duTa1LkA=="
    },
    "likes_count": 2,
    "answers": []
  },
  {
    "id": 17894873804240518,
    "created_at": 1631687294,
    
    "owner": {
      "id": "d6rxejcqWY4WQK-6N79Y4Q==",
      "username": "QK3Q9rL8e0gfgIIkHudCbg=="
    },
    "likes_count": 1,
    "answers": []
  },
  {
    "id": 17900007422273399,
    "created_at": 1631687280,
    
    "owner": {
      "id": "HCN-MrNGAtQxehsk2As02g==",
      "username": "g4TGzVcNT8L_K88656o1SA=="
    },
    "likes_count": 1,
    "answers": []
  },
  {
    "id": 17947461961552176,
    "created_at": 1631687218,
    
    "owner": {
      "id": "iGxyIN_G4IZJfyC9R9S0lA==",
      "username": "iIGca3MdQ_zyTREZiyOHwQ=="
    },
    "likes_count": 6,
    "answers": [
      {
        "id": 17970578173437205,
        "created_at": 1631693177,
        
        "owner": {
          "id": "E8ALt2CLomIxAph0by-CUQ==",
          "username": "mS-5TshgaiX-6Ah3gloGnA=="
        },
        "likes_count": 2
      },
      {
        "id": 17917385989853117,
        "created_at": 1631688183,
        
        "owner": {
          "id": "iGxyIN_G4IZJfyC9R9S0lA==",
          "username": "iIGca3MdQ_zyTREZiyOHwQ=="
        },
        "likes_count": 1
      },
      {
        "id": 17899950881321930,
        "created_at": 1631696498,
        
        "owner": {
          "id": "iGxyIN_G4IZJfyC9R9S0lA==",
          "username": "iIGca3MdQ_zyTREZiyOHwQ=="
        },
        "likes_count": 3
      },
      {
        "id": 17889420581415687,
        "created_at": 1631687963,
        
        "owner": {
          "id": "9rICyTfoSV8xPafAZ0Xo0w==",
          "username": "hib4mKmHA-vgwtwb0Q_04A=="
        },
        "likes_count": 16
      }
    ]
  },
  {
    "id": 17921447839783034,
    "created_at": 1631687111,
    
    "owner": {
      "id": "sEFF4N6XwdS5DXWd2ptSXQ==",
      "username": "GFQ5qppTwb98v4TN4lko1Q=="
    },
    "likes_count": 1,
    "answers": []
  },
  {
    "id": 17912396858016181,
    "created_at": 1631687096,
    
    "owner": {
      "id": "ify18xh1e8ju9GsmxIKqtw==",
      "username": "4OeZsH6jQ-drWUSUsAls9g=="
    },
    "likes_count": 1,
    "answers": []
  },
  {
    "id": 17942455987574064,
    "created_at": 1631687079,
    
    "owner": {
      "id": "dPTNlbSEaAdiGhjpg4YFRA==",
      "username": "7QStKD0ni01rq5L3xQOZkA=="
    },
    "likes_count": 2,
    "answers": []
  },
  {
    "id": 17900971520316726,
    "created_at": 1631686884,
    
    "owner": {
      "id": "0JGy1vW9l58a9uf5oEdpLw==",
      "username": "kaLhFxgcO_vBDDvxpYIEDw=="
    },
    "likes_count": 12,
    "answers": [
      {
        "id": 17996434081370387,
        "created_at": 1631687661,
        
        "owner": {
          "id": "9rICyTfoSV8xPafAZ0Xo0w==",
          "username": "hib4mKmHA-vgwtwb0Q_04A=="
        },
        "likes_count": 16
      }
    ]
  },
  {
    "id": 17894035331243956,
    "created_at": 1631686645,
    
    "owner": {
      "id": "CATLVjpITboZENFX8P-v7A==",
      "username": "jv4uq0dsiHc3qV9Owgx0jw=="
    },
    "likes_count": 29,
    "answers": [
      {
        "id": 18105404323254705,
        "created_at": 1631686997,
        
        "owner": {
          "id": "CATLVjpITboZENFX8P-v7A==",
          "username": "jv4uq0dsiHc3qV9Owgx0jw=="
        },
        "likes_count": 3
      },
      {
        "id": 17952908602506739,
        "created_at": 1631703877,
        
        "owner": {
          "id": "Wzg5SOT0-bTxthgQ6nosjA==",
          "username": "TPoGBOepiVdh2KqBS05KFw=="
        },
        "likes_count": 0
      },
      {
        "id": 17893494605340578,
        "created_at": 1631686912,
        
        "owner": {
          "id": "ify18xh1e8ju9GsmxIKqtw==",
          "username": "4OeZsH6jQ-drWUSUsAls9g=="
        },
        "likes_count": 3
      }
    ]
  },
  {
    "id": 17915985202872651,
    "created_at": 1631686449,
    
    "owner": {
      "id": "ZfOBzTsXsuMcr8CVnzufKg==",
      "username": "UPkZgojx2Xaqa9keenrD0A=="
    },
    "likes_count": 8,
    "answers": []
  },
  {
    "id": 18145463833201755,
    "created_at": 1631686358,
    
    "owner": {
      "id": "kkpEEZAOkYzyTEHUOIn0Sw==",
      "username": "4AuyqQm7lDOCIytQt7kJZw=="
    },
    "likes_count": 3,
    "answers": []
  },
  {
    "id": 17921004034792703,
    "created_at": 1631686201,
    
    "owner": {
      "id": "Wzg5SOT0-bTxthgQ6nosjA==",
      "username": "TPoGBOepiVdh2KqBS05KFw=="
    },
    "likes_count": 63,
    "answers": [
      {
        "id": 18189939433185546,
        "created_at": 1631687917,
        
        "owner": {
          "id": "Q_aC_QwQkyZ5zdIA6Nae5w==",
          "username": "SsOy-Ai01WK5BtR-496zfQ=="
        },
        "likes_count": 7
      }
    ]
  },
  {
    "id": 17931971908673240,
    "created_at": 1631686184,
    
    "owner": {
      "id": "Pq-zYHZP99iDkY2_Cocavw==",
      "username": "NtDKZtZcYWa3qMmPtIt1Lg=="
    },
    "likes_count": 6,
    "answers": []
  },
  {
    "id": 17909467670090674,
    "created_at": 1631685799,
    
    "owner": {
      "id": "9rICyTfoSV8xPafAZ0Xo0w==",
      "username": "hib4mKmHA-vgwtwb0Q_04A=="
    },
    "likes_count": 227,
    "answers": [
      {
        "id": 18093601621276852,
        "created_at": 1631687850,
        
        "owner": {
          "id": "tDVHSLHhaXUjmE5of9jfug==",
          "username": "1qcBbjjTICnOo5PlMl3PlA=="
        },
        "likes_count": 0
      },
      {
        "id": 17928123778744739,
        "created_at": 1631687010,
        
        "owner": {
          "id": "ify18xh1e8ju9GsmxIKqtw==",
          "username": "4OeZsH6jQ-drWUSUsAls9g=="
        },
        "likes_count": 17
      }
    ]
  }
]