[
  {
    "id": 17913192656239020,
    "created_at": 1645338147,
    
    "owner": {
      "id": "8SGzvUmGkHk9rrns-_wk_g==",
      "username": "WuEMPFd8GYKWjm2aFznWsw=="
    },
    "likes_count": 20,
    "answers": []
  },
  {
    "id": 17929957175027343,
    "created_at": 1645274313,
    
    "owner": {
      "id": "HtBdmcFzNuoGhtoQLvwcyg==",
      "username": "S-KrpNxR1Ri7radG7g8_vg=="
    },
    "likes_count": 3,
    "answers": []
  },
  {
    "id": 18007922044383909,
    "created_at": 1645267066,
    
    "owner": {
      "id": "_jpJ63fwT1-ANXwX8HF-wA==",
      "username": "jWjWVtovHMnattQv791LJA=="
    },
    "likes_count": 16,
    "answers": []
  },
  {
    "id": 18126971062255045,
    "created_at": 1644487225,
    
    "owner": {
      "id": "_zLVnU8ARcZj7xB-TE445Q==",
      "username": "uFWEdHBWkxKfT4nG50xAkw=="
    },
    "likes_count": 20,
    "answers": [
      {
        "id": 17967116395496773,
        "created_at": 1645180029,
        
        "owner": {
          "id": "jG9UIFwJJrdQ1OCZZwtZlA==",
          "username": "2wvgdncshkVi9Ofe4ai0sg=="
        },
        "likes_count": 1
      },
      {
        "id": 17938790296799058,
        "created_at": 1645144610,
        
        "owner": {
          "id": "jG9UIFwJJrdQ1OCZZwtZlA==",
          "username": "2wvgdncshkVi9Ofe4ai0sg=="
        },
        "likes_count": 1
      },
      {
        "id": 17860764188657238,
        "created_at": 1645164051,
        
        "owner": {
          "id": "_zLVnU8ARcZj7xB-TE445Q==",
          "username": "uFWEdHBWkxKfT4nG50xAkw=="
        },
        "likes_count": 6
      }
    ]
  },
  {
    "id": 17951841178642368,
    "created_at": 1643976170,
    
    "owner": {
      "id": "6FyBWNWE0fwmr9I4105k6A==",
      "username": "sIgUVhnyVubHn-d3IVnIGA=="
    },
    "likes_count": 11,
    "answers": []
  },
  {
    "id": 18006119800377996,
    "created_at": 1643963157,
    
    "owner": {
      "id": "aowcneB-0avlHZhmgIe1ow==",
      "username": "MztS2gDIsntkjw3F268A_A=="
    },
    "likes_count": 4,
    "answers": []
  },
  {
    "id": 18278048755025040,
    "created_at": 1643959500,
    
    "owner": {
      "id": "HK_qghrhj3ustXzrygoKrg==",
      "username": "RdE829xqrRrGF5oE3jLkog=="
    },
    "likes_count": 0,
    "answers": []
  },
  {
    "id": 17927645081037786,
    "created_at": 1643932992,
    
    "owner": {
      "id": "JkvUDtGOcBEZiQ1UL9qCrQ==",
      "username": "UWs9LBfRliGbmXUIBCBAgw=="
    },
    "likes_count": 0,
    "answers": []
  },
  {
    "id": 17898672815436131,
    "created_at": 1643911824,
    
    "owner": {
      "id": "MJUHcq3d7NeGt7bOyDI9WA==",
      "username": "_3jh0wrg1egfG9E6qu7Fqg=="
    },
    "likes_count": 0,
    "answers": []
  },
  {
    "id": 17951930824633588,
    "created_at": 1643900433,
    
    "owner": {
      "id": "34J8mPUp25QPXsisEgMrgQ==",
      "username": "Ts2Y1OaSukvLBsmm51HdTQ=="
    },
    "likes_count": 0,
    "answers": []
  },
  {
    "id": 17903784371514381,
    "created_at": 1643849106,
    
    "owner": {
      "id": "efEBU8C4x4Vn42VaIVeB-w==",
      "username": "TJfJaiGGI_U0cfTIew_XaQ=="
    },
    "likes_count": 1,
    "answers": []
  },
  {
    "id": 17953082824590578,
    "created_at": 1643835806,
    
    "owner": {
      "id": "SbUcJaee4T9XfNLdZG_nLg==",
      "username": "27CcEljrX-rFMBhtGanIpg=="
    },
    "likes_count": 0,
    "answers": []
  },
  {
    "id": 17858356919690327,
    "created_at": 1643833896,
    
    "owner": {
      "id": "ydS45nSJCdaRiZP1PUo6Lw==",
      "username": "KZW__t4SS0EltwMKRcVlIg=="
    },
    "likes_count": 0,
    "answers": []
  },
  {
    "id": 17896804871528350,
    "created_at": 1643823370,
    
    "owner": {
      "id": "4uIGc6JhA8zMw6XOiR6vKw==",
      "username": "EB3aHrqM9byU13Bjm63GCQ=="
    },
    "likes_count": 0,
    "answers": []
  },
  {
    "id": 17952391714643587,
    "created_at": 1643818808,
    
    "owner": {
      "id": "_b6iJ28JYL3mTKBCsH-mZg==",
      "username": "0V64IYREpxceEr13nCe6DA=="
    },
    "likes_count": 0,
    "answers": []
  },
  {
    "id": 18196807555148762,
    "created_at": 1643814328,
    
    "owner": {
      "id": "89xJbvfTxID--a2n234Slw==",
      "username": "EaOyEmFElYuVdx6GldldRg=="
    },
    "likes_count": 0,
    "answers": []
  },
  {
    "id": 17952626716720922,
    "created_at": 1643807839,
    
    "owner": {
      "id": "MbFmIgDq7dx5s_e5TnN7KQ==",
      "username": "8Z4cvypaWWOZ5UIv3kqetQ=="
    },
    "likes_count": 0,
    "answers": []
  },
  {
    "id": 17922643169150597,
    "created_at": 1643807616,
    
    "owner": {
      "id": "K9GRHacAYQFUlXhCCdSnbA==",
      "username": "TysNucz6neILq3tuoRzX3w=="
    },
    "likes_count": 8,
    "answers": [
      {
        "id": 17911747748471207,
        "created_at": 1643811240,
        
        "owner": {
          "id": "0Dkmc9y-X4yNn-nJfKKh4w==",
          "username": "NwVqWOjO0yaZxQKT9vN4Gw=="
        },
        "likes_count": 2
      },
      {
        "id": 17906702600416059,
        "created_at": 1643829967,
        
        "owner": {
          "id": "p2C23cl91q3lhPA3wjf-sg==",
          "username": "et56RH9R_lxur_N_USpG3w=="
        },
        "likes_count": 10
      }
    ]
  },
  {
    "id": 17911343933489524,
    "created_at": 1643805695,
    
    "owner": {
      "id": "X6IpKGYx884vg68Wpe5XOg==",
      "username": "IZpp8FOSqQKSZVC42Oob2Q=="
    },
    "likes_count": 3,
    "answers": [
      {
        "id": 18125840182254641,
        "created_at": 1643879050,
        
        "owner": {
          "id": "s_9BC-3j4rF-SekgRIxg6Q==",
          "username": "tN_uuLQJkF121feNKWdD3Q=="
        },
        "likes_count": 5
      },
      {
        "id": 17887276349511977,
        "created_at": 1644180739,
        
        "owner": {
          "id": "TrW9S7TMSohUnANam7f_OA==",
          "username": "1lUymH5vHBjZyqEcv3xaRw=="
        },
        "likes_count": 2
      }
    ]
  },
  {
    "id": 17862002288674135,
    "created_at": 1643795842,
    
    "owner": {
      "id": "Pdg0fZEODwPRtJTwtllz4Q==",
      "username": "hPIOC4efF5SENvG7dIzHMw=="
    },
    "likes_count": 0,
    "answers": []
  },
  {
    "id": 17948909734676370,
    "created_at": 1643793907,
    
    "owner": {
      "id": "lJSxfCoaDmb1cgJtiAp7jQ==",
      "username": "UZT3oQBcIZ0B1vJlzgIR0Q=="
    },
    "likes_count": 0,
    "answers": []
  },
  {
    "id": 17917819379245788,
    "created_at": 1643792837,
    
    "owner": {
      "id": "fifnauuJX-4YKVjLd_z3Jw==",
      "username": "FnsFiHYoKGFXyU8j0785xw=="
    },
    "likes_count": 0,
    "answers": []
  },
  {
    "id": 17936868781799368,
    "created_at": 1643788166,
    
    "owner": {
      "id": "7T-WqDsn7S3FaZv7zh2Z0g==",
      "username": "H47ZTlxQpdt1nNFuHcEiHw=="
    },
    "likes_count": 0,
    "answers": [
      {
        "id": 18114738934279906,
        "created_at": 1645276865,
        
        "owner": {
          "id": "7T-WqDsn7S3FaZv7zh2Z0g==",
          "username": "H47ZTlxQpdt1nNFuHcEiHw=="
        },
        "likes_count": 0
      }
    ]
  },
  {
    "id": 17917305452112216,
    "created_at": 1643787295,
    
    "owner": {
      "id": "aaRKpNa7vkji3l4sH1rNWQ==",
      "username": "m9h3CwuBocANvcxy9xBvyg=="
    },
    "likes_count": 0,
    "answers": []
  },
  {
    "id": 17889994028571556,
    "created_at": 1643786743,
    
    "owner": {
      "id": "_ru-REOFKISKVZFiLEHsaQ==",
      "username": "3FIMxHWTQcDfXTuNrR093A=="
    },
    "likes_count": 8,
    "answers": [
      {
        "id": 18001756129402596,
        "created_at": 1643853809,
        
        "owner": {
          "id": "BSTJAC-CC62Iij9m8VupaA==",
          "username": "j3mch-S4lbOiJcC7-3yF8g=="
        },
        "likes_count": 0
      },
      {
        "id": 17906896211410525,
        "created_at": 1643797443,
        
        "owner": {
          "id": "BSTJAC-CC62Iij9m8VupaA==",
          "username": "j3mch-S4lbOiJcC7-3yF8g=="
        },
        "likes_count": 0
      },
      {
        "id": 17855955302669743,
        "created_at": 1643840462,
        
        "owner": {
          "id": "fFOSTM7iettDZ_AD8Y6Msw==",
          "username": "txntug19ltMK9ksj1_CXEg=="
        },
        "likes_count": 0
      }
    ]
  },
  {
    "id": 17866061321660949,
    "created_at": 1643785726,
    
    "owner": {
      "id": "xIMr4XKLFB_HF1luo8XWEg==",
      "username": "Tem2SePFt6EF_8rr11q23Q=="
    },
    "likes_count": 154,
    "answers": [
      {
        "id": 17939952631854733,
        "created_at": 1643903996,
        
        "owner": {
          "id": "KqQAUI2-IEukORlbiWL0sA==",
          "username": "W5BT88ANIu05gN54of8zKA=="
        },
        "likes_count": 0
      },
      {
        "id": 17910562802468800,
        "created_at": 1643799515,
        
        "owner": {
          "id": "Dv0dQss_zhOtfAvzYewOQA==",
          "username": "iKkjqHKN7SpI0yEhl3bipg=="
        },
        "likes_count": 7
      }
    ]
  },
  {
    "id": 17918383862204790,
    "created_at": 1643785462,
    
    "owner": {
      "id": "jJVpaVZfGAaer46MvIY8fw==",
      "username": "o75G4wE321TqaZ-fMOOeMg=="
    },
    "likes_count": 1,
    "answers": []
  },
  {
    "id": 17950557139659355,
    "created_at": 1643784532,
    
    "owner": {
      "id": "eOoxAa7fF98LK75pTkI6LQ==",
      "username": "zJHQeWA8Zx-hnfwmiDyAiw=="
    },
    "likes_count": 1,
    "answers": []
  },
  {
    "id": 18143707282244018,
    "created_at": 1643784410,
    
    "owner": {
      "id": "FfbIb_UBpulCAbyEwq891w==",
      "username": "LVsVpMgnttj0mdF_LAFtNw=="
    },
    "likes_count": 14,
    "answers": []
  },
  {
    "id": 18255852589079657,
    "created_at": 1643784404,
    
    "owner": {
      "id": "oc-E12TvQgt9DuokIOiVLg==",
      "username": "EptteMlBVCVdxJdxylvjIw=="
    },
    "likes_count": 1,
    "answers": [
      {
        "id": 18114333667302063,
        "created_at": 1643788335,
        
        "owner": {
          "id": "oU2nZplMIj9ZuKS4CBgcHw==",
          "username": "_-Z3Aa9egpVnN7a_milzyQ=="
        },
        "likes_count": 9
      },
      {
        "id": 18112916542281965,
        "created_at": 1643784979,
        
        "owner": {
          "id": "3ZViKa-Bp453h6IlLUpvow==",
          "username": "T2YUUJpZtxq7GjPntr2JgA=="
        },
        "likes_count": 31
      },
      {
        "id": 17928193625041497,
        "created_at": 1643814879,
        
        "owner": {
          "id": "7hUL0AlifGmWUSux-Sj0bQ==",
          "username": "OWManVSqgChIoLMdvYBSCA=="
        },
        "likes_count": 2
      }
    ]
  },
  {
    "id": 18196815547183362,
    "created_at": 1643784311,
    
    "owner": {
      "id": "7lHh8TEyUfPFsKu2xXgeiA==",
      "username": "ogDNzZg8Ay68KIavvv279w=="
    },
    "likes_count": 2,
    "answers": [
      {
        "id": 18031642768331911,
        "created_at": 1643813488,
        
        "owner": {
          "id": "BgHwq7d7GwT4br6aRwD6iA==",
          "username": "J73HYFZEN1cUbwDvddKTIQ=="
        },
        "likes_count": 8
      },
      {
        "id": 17955443959609701,
        "created_at": 1643969030,
        
        "owner": {
          "id": "_T_gB1TvOTfo37dpJG9cuQ==",
          "username": "9bU7A9ahWNhSaoMCAOTbOg=="
        },
        "likes_count": 1
      },
      {
        "id": 17923488110024288,
        "created_at": 1643792103,
        
        "owner": {
          "id": "BgHwq7d7GwT4br6aRwD6iA==",
          "username": "J73HYFZEN1cUbwDvddKTIQ=="
        },
        "likes_count": 7
      },
      {
        "id": 17897455646444834,
        "created_at": 1643811057,
        
        "owner": {
          "id": "0Dkmc9y-X4yNn-nJfKKh4w==",
          "username": "NwVqWOjO0yaZxQKT9vN4Gw=="
        },
        "likes_count": 4
      }
    ]
  },
  {
    "id": 18125713225250120,
    "created_at": 1643784097,
    
    "owner": {
      "id": "9Zb3EhH9JK88u1FjE-Lo2w==",
      "username": "3T4FXCMsTWUSMh9Ir0eF7Q=="
    },
    "likes_count": 0,
    "answers": []
  },
  {
    "id": 17909176538276602,
    "created_at": 1643783779,
    
    "owner": {
      "id": "oc-E12TvQgt9DuokIOiVLg==",
      "username": "EptteMlBVCVdxJdxylvjIw=="
    },
    "likes_count": 0,
    "answers": []
  },
  {
    "id": 17954918410565077,
    "created_at": 1643783043,
    
    "owner": {
      "id": "2k-YLHrDIOIAmqyLra1xJw==",
      "username": "qxu-iVHIGqPD1cJ0NC3U7g=="
    },
    "likes_count": 1,
    "answers": []
  },
  {
    "id": 17964815626540138,
    "created_at": 1643781974,
    
    "owner": {
      "id": "6YocgRsu-1gAYHkHM4QMcA==",
      "username": "a7j4BuRhjhk-QyIs2HeWmg=="
    },
    "likes_count": 3,
    "answers": []
  },
  {
    "id": 17890911587578311,
    "created_at": 1643780474,
    
    "owner": {
      "id": "QIgrU5vzqLuP0wnXI_RBew==",
      "username": "M03sSUs3rM1W75EkGP7cUA=="
    },
    "likes_count": 1,
    "answers": [
      {
        "id": 18002301859398900,
        "created_at": 1643788803,
        
        "owner": {
          "id": "oU2nZplMIj9ZuKS4CBgcHw==",
          "username": "_-Z3Aa9egpVnN7a_milzyQ=="
        },
        "likes_count": 6
      }
    ]
  },
  {
    "id": 17977523902475063,
    "created_at": 1643780066,
    
    "owner": {
      "id": "aSN_vYhaA23TBt1DfxBXPg==",
      "username": "dHq8-vrXZqMvtDC_cWbMJA=="
    },
    "likes_count": 0,
    "answers": [
      {
        "id": 17997652717408562,
        "created_at": 1644181460,
        
        "owner": {
          "id": "TrW9S7TMSohUnANam7f_OA==",
          "username": "1lUymH5vHBjZyqEcv3xaRw=="
        },
        "likes_count": 0
      },
      {
        "id": 17940103387847106,
        "created_at": 1643797624,
        
        "owner": {
          "id": "IgglcwCWwSXDwhyrQbLYEg==",
          "username": "3VX-tKEoGnCx3hYbLUPX-Q=="
        },
        "likes_count": 0
      },
      {
        "id": 17891680091552939,
        "created_at": 1643798069,
        
        "owner": {
          "id": "aSN_vYhaA23TBt1DfxBXPg==",
          "username": "dHq8-vrXZqMvtDC_cWbMJA=="
        },
        "likes_count": 0
      }
    ]
  },
  {
    "id": 17943443404806743,
    "created_at": 1643779926,
    
    "owner": {
      "id": "lEuFEjU2ieZLGKjN6IUIng==",
      "username": "kFA4K8sTsfaoziO6QkGabw=="
    },
    "likes_count": 2,
    "answers": [
      {
        "id": 17899846319394795,
        "created_at": 1643793108,
        
        "owner": {
          "id": "EEIOB_vLT2k5IVWLXLFw3g==",
          "username": "h8l-p49lEWGUJxBcrAQGtg=="
        },
        "likes_count": 6
      }
    ]
  },
  {
    "id": 18015323896368212,
    "created_at": 1643779650,
    
    "owner": {
      "id": "Lb0EQkE3eMHgWyJWr05u_A==",
      "username": "UxOz2QGOltJ6qMUjTWspXA=="
    },
    "likes_count": 11,
    "answers": []
  },
  {
    "id": 17897217269461753,
    "created_at": 1643779393,
    
    "owner": {
      "id": "LB6XvNlHr9RMpv6H-3PwgA==",
      "username": "Hzim7kODoe8807FBZaripw=="
    },
    "likes_count": 6,
    "answers": [
      {
        "id": 18147115207220913,
        "created_at": 1643799187,
        
        "owner": {
          "id": "yUUm05HKAxY7oF2oHxdheQ==",
          "username": "0YHHRzH8s15czP1aCg_paQ=="
        },
        "likes_count": 2
      },
      {
        "id": 17947723009742356,
        "created_at": 1645342053,
        
        "owner": {
          "id": "aaRKpNa7vkji3l4sH1rNWQ==",
          "username": "m9h3CwuBocANvcxy9xBvyg=="
        },
        "likes_count": 1
      },
      {
        "id": 17936280943916079,
        "created_at": 1643890148,
        
        "owner": {
          "id": "yUUm05HKAxY7oF2oHxdheQ==",
          "username": "0YHHRzH8s15czP1aCg_paQ=="
        },
        "likes_count": 1
      },
      {
        "id": 17933505259940106,
        "created_at": 1643837663,
        
        "owner": {
          "id": "Ny_ZNO4pUr_Zm2I4n2clkA==",
          "username": "6TkkKZ-KiZAT-8eJymNciQ=="
        },
        "likes_count": 0
      },
      {
        "id": 17932931110943896,
        "created_at": 1643811466,
        
        "owner": {
          "id": "yUUm05HKAxY7oF2oHxdheQ==",
          "username": "0YHHRzH8s15czP1aCg_paQ=="
        },
        "likes_count": 0
      },
      {
        "id": 17909679209371303,
        "created_at": 1643806653,
        
        "owner": {
          "id": "LB6XvNlHr9RMpv6H-3PwgA==",
          "username": "Hzim7kODoe8807FBZaripw=="
        },
        "likes_count": 1
      },
      {
        "id": 17900588765385116,
        "created_at": 1643838889,
        
        "owner": {
          "id": "Ny_ZNO4pUr_Zm2I4n2clkA==",
          "username": "6TkkKZ-KiZAT-8eJymNciQ=="
        },
        "likes_count": 2
      },
      {
        "id": 17848637141715844,
        "created_at": 1643838813,
        
        "owner": {
          "id": "LB6XvNlHr9RMpv6H-3PwgA==",
          "username": "Hzim7kODoe8807FBZaripw=="
        },
        "likes_count": 1
      }
    ]
  },
  {
    "id": 18005490106383699,
    "created_at": 1643779102,
    
    "owner": {
      "id": "SjJ5Ckgz4HyT9nqjgm_nQA==",
      "username": "sAZx-llKj_QD4BtEJ1imxw=="
    },
    "likes_count": 2,
    "answers": []
  },
  {
    "id": 17943473338718553,
    "created_at": 1643771105,
    
    "owner": {
      "id": "D4ixeZV-MJbHefDnD_JhoA==",
      "username": "Ckj4KMArlxxGt7nKa7yCrg=="
    },
    "likes_count": 0,
    "answers": []
  },
  {
    "id": 17935530883906837,
    "created_at": 1643760111,
    
    "owner": {
      "id": "S81n33eE0CalT-2VUYWVfQ==",
      "username": "R8B3dKX7XUjfwCzyLI9IIQ=="
    },
    "likes_count": 4,
    "answers": []
  },
  {
    "id": 17843790053727695,
    "created_at": 1643757120,
    
    "owner": {
      "id": "xI-5786eLb7GhQ7DYr4qKA==",
      "username": "SA_fyLz6iJteo3a0nS4gJw=="
    },
    "likes_count": 6,
    "answers": [
      {
        "id": 18187003978094000,
        "created_at": 1643760795,
        
        "owner": {
          "id": "k6__7CoAk8rS5Cu608TbHQ==",
          "username": "d4mq5RiipG8hQ2RqJu8AvA=="
        },
        "likes_count": 0
      },
      {
        "id": 17946349111696738,
        "created_at": 1643768533,
        
        "owner": {
          "id": "xI-5786eLb7GhQ7DYr4qKA==",
          "username": "SA_fyLz6iJteo3a0nS4gJw=="
        },
        "likes_count": 7
      }
    ]
  },
  {
    "id": 17903907038511582,
    "created_at": 1643756570,
    
    "owner": {
      "id": "A6SPnLUgQz4dz87_9YRyig==",
      "username": "3Lri7y4IURwRCgPOV61qTg=="
    },
    "likes_count": 8,
    "answers": []
  },
  {
    "id": 17941615732831279,
    "created_at": 1643755455,
    
    "owner": {
      "id": "ZtIVr7ijER6Rf93-baxwOA==",
      "username": "WaL1_3NIbXQuY-kVvn77Pg=="
    },
    "likes_count": 12,
    "answers": [
      {
        "id": 17932314856952173,
        "created_at": 1643784333,
        
        "owner": {
          "id": "oc-E12TvQgt9DuokIOiVLg==",
          "username": "EptteMlBVCVdxJdxylvjIw=="
        },
        "likes_count": 0
      }
    ]
  },
  {
    "id": 18040544407317033,
    "created_at": 1643754913,
    
    "owner": {
      "id": "jWN7K6DbBQJ5THlehb1Kiw==",
      "username": "aFxW_7YmPKf76wH1gzpyQA=="
    },
    "likes_count": 5,
    "answers": [
      {
        "id": 18277217080028614,
        "created_at": 1643788882,
        
        "owner": {
          "id": "oU2nZplMIj9ZuKS4CBgcHw==",
          "username": "_-Z3Aa9egpVnN7a_milzyQ=="
        },
        "likes_count": 2
      },
      {
        "id": 17951514817719313,
        "created_at": 1643806981,
        
        "owner": {
          "id": "oU2nZplMIj9ZuKS4CBgcHw==",
          "username": "_-Z3Aa9egpVnN7a_milzyQ=="
        },
        "likes_count": 0
      },
      {
        "id": 17951478772638175,
        "created_at": 1643806968,
        
        "owner": {
          "id": "oU2nZplMIj9ZuKS4CBgcHw==",
          "username": "_-Z3Aa9egpVnN7a_milzyQ=="
        },
        "likes_count": 1
      },
      {
        "id": 17845277252706853,
        "created_at": 1643796415,
        
        "owner": {
          "id": "jWN7K6DbBQJ5THlehb1Kiw==",
          "username": "aFxW_7YmPKf76wH1gzpyQA=="
        },
        "likes_count": 1
      }
    ]
  },
  {
    "id": 17971892455466507,
    "created_at": 1643754452,
    
    "owner": {
      "id": "tHhsBln1Eg07izmyBHwkfg==",
      "username": "nDED6rWXM5XQlTK5S5OFXw=="
    },
    "likes_count": 62,
    "answers": []
  },
  {
    "id": 17928974734904025,
    "created_at": 1643754382,
    
    "owner": {
      "id": "Ci5tz_rap6Qw7dTVjA98Og==",
      "username": "owJNaekVOQmsf2nPCJmWmA=="
    },
    "likes_count": 15,
    "answers": [
      {
        "id": 18023582098347988,
        "created_at": 1643795011,
        
        "owner": {
          "id": "v6blQ2eEv2Ugusegh3k7tA==",
          "username": "LeihrlbT4IlPPFCIg5wYmA=="
        },
        "likes_count": 0
      },
      {
        "id": 18015410194369380,
        "created_at": 1643781096,
        
        "owner": {
          "id": "ql6rL82w-PRxK7smRg750Q==",
          "username": "59QE0qmyrnk-jeq8aQKihg=="
        },
        "likes_count": 33
      },
      {
        "id": 17941098112807622,
        "created_at": 1643805028,
        
        "owner": {
          "id": "Ci5tz_rap6Qw7dTVjA98Og==",
          "username": "owJNaekVOQmsf2nPCJmWmA=="
        },
        "likes_count": 0
      },
      {
        "id": 17938949410873615,
        "created_at": 1643781790,
        
        "owner": {
          "id": "-hiwQpfuoJzb9rjTP812IQ==",
          "username": "pKhyddYPnf09s-sta3lv-A=="
        },
        "likes_count": 2
      },
      {
        "id": 17928691931023054,
        "created_at": 1643784781,
        
        "owner": {
          "id": "3ZViKa-Bp453h6IlLUpvow==",
          "username": "T2YUUJpZtxq7GjPntr2JgA=="
        },
        "likes_count": 12
      },
      {
        "id": 17918799473102614,
        "created_at": 1643806992,
        
        "owner": {
          "id": "3ZViKa-Bp453h6IlLUpvow==",
          "username": "T2YUUJpZtxq7GjPntr2JgA=="
        },
        "likes_count": 7
      }
    ]
  },
  {
    "id": 17934168883940150,
    "created_at": 1643754354,
    
    "owner": {
      "id": "A05u89IO9R_FTxKCHT8Vbg==",
      "username": "551j9s9bUqHdxtJgai4EMg=="
    },
    "likes_count": 223,
    "answers": [
      {
        "id": 17941427791831211,
        "created_at": 1643788824,
        
        "owner": {
          "id": "NLfFQhpWIM7lpGyLBuRSpw==",
          "username": "8m1C9hIU-RWNCt6KzzVLIw=="
        },
        "likes_count": 4
      },
      {
        "id": 17902119821361029,
        "created_at": 1643755262,
        
        "owner": {
          "id": "9rICyTfoSV8xPafAZ0Xo0w==",
          "username": "hib4mKmHA-vgwtwb0Q_04A=="
        },
        "likes_count": 77
      }
    ]
  },
  {
    "id": 17926466347977835,
    "created_at": 1643754217,
    
    "owner": {
      "id": "BE-_zXWgX8lI-FgM6TkvJQ==",
      "username": "i6eyS2Fg9UwtcOXv7mpuQg=="
    },
    "likes_count": 155,
    "answers": [
      {
        "id": 17937631507787215,
        "created_at": 1643786958,
        
        "owner": {
          "id": "vXYhfombDh1XcBekvz5iCA==",
          "username": "oSAnYyacvqJAHL4VL7SNjA=="
        },
        "likes_count": 8
      }
    ]
  },
  {
    "id": 17930365927992747,
    "created_at": 1643754176,
    
    "owner": {
      "id": "tHhsBln1Eg07izmyBHwkfg==",
      "username": "nDED6rWXM5XQlTK5S5OFXw=="
    },
    "likes_count": 22,
    "answers": [
      {
        "id": 17910465134248007,
        "created_at": 1643755187,
        
        "owner": {
          "id": "28Wd_AHxSuWqNU5zZNq0aQ==",
          "username": "j3HEmmGO78vpn_vYdd7pIA=="
        },
        "likes_count": 4
      }
    ]
  },
  {
    "id": 18161524648204836,
    "created_at": 1643754172,
    
    "owner": {
      "id": "WCvKFQOJZ9Nps46QU5naiw==",
      "username": "Fy-DLa3DTwl8nhY6R4Sr0A=="
    },
    "likes_count": 21,
    "answers": [
      {
        "id": 17997544057407863,
        "created_at": 1643754598,
        
        "owner": {
          "id": "WCvKFQOJZ9Nps46QU5naiw==",
          "username": "Fy-DLa3DTwl8nhY6R4Sr0A=="
        },
        "likes_count": 15
      },
      {
        "id": 17933420740860370,
        "created_at": 1643754620,
        
        "owner": {
          "id": "WCvKFQOJZ9Nps46QU5naiw==",
          "username": "Fy-DLa3DTwl8nhY6R4Sr0A=="
        },
        "likes_count": 6
      }
    ]
  },
  {
    "id": 17945320582742675,
    "created_at": 1643753978,
    
    "owner": {
      "id": "lxrBzgRj8QYYtV041DxGsA==",
      "username": "jH7y9dK1uTMPZud3IHBYZQ=="
    },
    "likes_count": 1,
    "answers": []
  },
  {
    "id": 17946476656738273,
    "created_at": 1643753833,
    
    "owner": {
      "id": "2DUjRcP0l1LY_fnVvV7SFQ==",
      "username": "Gyus-a5LYx0Q8wlPBkxWfA=="
    },
    "likes_count": 7,
    "answers": [
      {
        "id": 17909606639371534,
        "created_at": 1643774264,
        
        "owner": {
          "id": "mmen9U1thh1Lth3FVp7NFw==",
          "username": "icuwUYdXeqcH7jP6zUDRAQ=="
        },
        "likes_count": 4
      }
    ]
  },
  {
    "id": 18164671768201651,
    "created_at": 1643753734,
    
    "owner": {
      "id": "UbpQYJCnCuyDyOKQicrO3g==",
      "username": "uYQa7PLBD2QpUmIfDzRWJg=="
    },
    "likes_count": 98,
    "answers": [
      {
        "id": 18039981427321850,
        "created_at": 1645295718,
        
        "owner": {
          "id": "8Vi9YP_nHOnkG-nTNSLSJQ==",
          "username": "e_Tf6dSJs5gCOLRfQy0rBg=="
        },
        "likes_count": 0
      },
      {
        "id": 17950932046638983,
        "created_at": 1643874905,
        
        "owner": {
          "id": "j8j_9qi1mcATYPTEEACe4A==",
          "username": "HOakd18kduZ1zxJOb3dFQg=="
        },
        "likes_count": 4
      },
      {
        "id": 17920907963067809,
        "created_at": 1643807704,
        
        "owner": {
          "id": "cmmjkLeZjNLtwIT70rngQg==",
          "username": "CEg0O4hYexAAGHWyZAS-oA=="
        },
        "likes_count": 11
      },
      {
        "id": 17911423481342642,
        "created_at": 1643753891,
        
        "owner": {
          "id": "9rICyTfoSV8xPafAZ0Xo0w==",
          "username": "hib4mKmHA-vgwtwb0Q_04A=="
        },
        "likes_count": 52
      }
    ]
  },
  {
    "id": 18023685265352291,
    "created_at": 1643753526,
    
    "owner": {
      "id": "YBzVWzSsDkRlhNb_O5A8pw==",
      "username": "bltmZte0ISamshOLmxiv_Q=="
    },
    "likes_count": 187,
    "answers": [
      {
        "id": 18022529455357574,
        "created_at": 1643976273,
        
        "owner": {
          "id": "6FyBWNWE0fwmr9I4105k6A==",
          "username": "sIgUVhnyVubHn-d3IVnIGA=="
        },
        "likes_count": 1
      },
      {
        "id": 18000888424401604,
        "created_at": 1643776045,
        
        "owner": {
          "id": "bbgmyMOQCdQJ0lTJMGmXVA==",
          "username": "UoRolkn5ek3lpcHtqrEUCA=="
        },
        "likes_count": 3
      },
      {
        "id": 17932560598958120,
        "created_at": 1643787924,
        
        "owner": {
          "id": "R_AANXMgBeiTz7xI9-zjzg==",
          "username": "rijdQZkmUQkeV6XwoYvt1w=="
        },
        "likes_count": 2
      }
    ]
  },
  {
    "id": 18150320791236603,
    "created_at": 1643753192,
    
    "owner": {
      "id": "nt_c6Jq08PDXHw1mMJSoVA==",
      "username": "LAxcHk7gN0Ip3ICtK_S9XQ=="
    },
    "likes_count": 0,
    "answers": []
  },
  {
    "id": 17952264229654198,
    "created_at": 1643752856,
    
    "owner": {
      "id": "9rICyTfoSV8xPafAZ0Xo0w==",
      "username": "hib4mKmHA-vgwtwb0Q_04A=="
    },
    "likes_count": 490,
    "answers": [
      {
        "id": 18204111082126776,
        "created_at": 1643806905,
        
        "owner": {
          "id": "WCvKFQOJZ9Nps46QU5naiw==",
          "username": "Fy-DLa3DTwl8nhY6R4Sr0A=="
        },
        "likes_count": 8
      },
      {
        "id": 17950723333640280,
        "created_at": 1643778760,
        
        "owner": {
          "id": "MJUHcq3d7NeGt7bOyDI9WA==",
          "username": "_3jh0wrg1egfG9E6qu7Fqg=="
        },
        "likes_count": 0
      },
      {
        "id": 17946229972739525,
        "created_at": 1643793612,
        
        "owner": {
          "id": "lJSxfCoaDmb1cgJtiAp7jQ==",
          "username": "UZT3oQBcIZ0B1vJlzgIR0Q=="
        },
        "likes_count": 1
      },
      {
        "id": 17941449052829320,
        "created_at": 1643789959,
        
        "owner": {
          "id": "BgHwq7d7GwT4br6aRwD6iA==",
          "username": "J73HYFZEN1cUbwDvddKTIQ=="
        },
        "likes_count": 10
      },
      {
        "id": 17939504887871138,
        "created_at": 1643781286,
        
        "owner": {
          "id": "MJUHcq3d7NeGt7bOyDI9WA==",
          "username": "_3jh0wrg1egfG9E6qu7Fqg=="
        },
        "likes_count": 2
      },
      {
        "id": 17930500277008631,
        "created_at": 1643754462,
        
        "owner": {
          "id": "PBYGuO1SNui8DfKWlmF8jA==",
          "username": "qokFBKZdObkx442rZIwquA=="
        },
        "likes_count": 12
      },
      {
        "id": 17927080882955902,
        "created_at": 1643791965,
        
        "owner": {
          "id": "RQR2zmjlzCBqHVfK5-jIXg==",
          "username": "aiLVueU2IOcUJMwBWqVxug=="
        },
        "likes_count": 4
      },
      {
        "id": 17926210472093774,
        "created_at": 1643756546,
        
        "owner": {
          "id": "WCvKFQOJZ9Nps46QU5naiw==",
          "username": "Fy-DLa3DTwl8nhY6R4Sr0A=="
        },
        "likes_count": 23
      },
      {
        "id": 17909962799358121,
        "created_at": 1643754273,
        
        "owner": {
          "id": "BgHwq7d7GwT4br6aRwD6iA==",
          "username": "J73HYFZEN1cUbwDvddKTIQ=="
        },
        "likes_count": 94
      },
      {
        "id": 17909152445273899,
        "created_at": 1643784336,
        
        "owner": {
          "id": "jGYWLZzBmLac2OfEZ75sxQ==",
          "username": "Wq_MOzQ2qzYO0n3gTCIrVA=="
        },
        "likes_count": 1
      },
      {
        "id": 17906872406395089,
        "created_at": 1643788544,
        
        "owner": {
          "id": "aqAWXR82u2-1cvcpkkPw2g==",
          "username": "-BYa_I3sZUtlRuXXuXKn-g=="
        },
        "likes_count": 1
      },
      {
        "id": 17867218664655070,
        "created_at": 1643806376,
        
        "owner": {
          "id": "7hUL0AlifGmWUSux-Sj0bQ==",
          "username": "OWManVSqgChIoLMdvYBSCA=="
        },
        "likes_count": 11
      },
      {
        "id": 17848352039716094,
        "created_at": 1643780559,
        
        "owner": {
          "id": "jGYWLZzBmLac2OfEZ75sxQ==",
          "username": "Wq_MOzQ2qzYO0n3gTCIrVA=="
        },
        "likes_count": 1
      }
    ]
  }
]